Workbook

Sheet INSTRUCCIONES
A1: PLANTILLA OFICIAL – RENDICIÓN DE CUENTAS (CAPTURA DE AVANCES 2024–2025)
A3: Objetivo | B3: Consolidar avances físicos, financieros y evidencias por meta del Plan de Desarrollo. Esta plantilla alimenta el informe y la plataforma de rendición.
A5: Qué diligenciar | B5: ÚNICAMENTE la hoja 'REGISTRO_AVANCES'. No modificar estructuras, listas ni la hoja 'PLAN_DESARROLLO'.
A7: Reglas | B7: 1) Un registro = una meta (ID_META) en un año. 2) Seleccione ID_META desde la lista (NO escribir a mano). 3) Adjunte evidencia: indique tipo y nombre de archivo/ruta. 4) Los porcentajes y cálculos se llenan automáticamente. 5) Si un campo no aplica, deje en blanco y explique en Observaciones.
A9: Campos obligatorios mínimos | B9: Año, Secretaría, ID_META, Avance ejecutado (si aplica), Presupuesto ejecutado (si aplica), Estado, Evidencia (tipo + archivo/ruta), Responsable.
A11: Fecha de corte | B11: Definir por la Alcaldía (ej.: 31/12/2025).

Sheet PLAN_DESARROLLO
A1: ID_META | B1: BPIM | C1: EJE | D1: SECTOR | E1: META_PRODUCTO | F1: META_CUATRIENIO | G1: OBS_PLAN
A2: META-001 | B2: 2024257770003 | C2: POR EL SUPATÁ SOÑADO AVANZAMOS JUNTOS EN LA LÍNEA ESTRATÉGICA SOCIAL | D2: EDUCACION | E2: Garantizar el 100% de transporte escolar de estudiantes que su institución educativa más cercana supere los 3 kilómetros de distancia desde la vivienda.
A3: META-002 | B3: 2024257770003 | C3: POR EL SUPATÁ SOÑADO AVANZAMOS JUNTOS EN LA LÍNEA ESTRATÉGICA SOCIAL | D3: EDUCACION | E3: Garantizar la gratuidad en la educación en el 100% de las Instituciones y sedes Educativas del municipio.
A4: META-003 | B4: 2024257770003 | C4: POR EL SUPATÁ SOÑADO AVANZAMOS JUNTOS EN LA LÍNEA ESTRATÉGICA SOCIAL | D4: EDUCACION | E4: Mantener la cobertura al 100% y fortalecer el servicio de los estudiantes con el servicio de alimentación escolar
A5: META-004 | B5: 2024257770003 | C5: POR EL SUPATÁ SOÑADO AVANZAMOS JUNTOS EN LA LÍNEA ESTRATÉGICA SOCIAL | D5: EDUCACION | E5: Fortalecer una estrategia extra curricular en fomento del idioma ingles
A6: META-005 | B6: 2024257770004 | C6: POR EL SUPATÁ SOÑADO AVANZAMOS JUNTOS EN LA LÍNEA ESTRATÉGICA SOCIAL | D6: EDUCACION | E6: Realizar 1 dotación de menaje en restaurante escolar de las diferentes sedes de las instituciones Nuestra Señora de la Salud y el Imparal.)
A7: META-006 | B7: 2024257770004 | C7: POR EL SUPATÁ SOÑADO AVANZAMOS JUNTOS EN LA LÍNEA ESTRATÉGICA SOCIAL | D7: EDUCACION | E7: Mejoramiento y/o mantenimiento en infraestructura de las instituciones educativas y sus sedes.
A8: META-007 | B8: 2024257770005 | C8: POR EL SUPATÁ SOÑADO AVANZAMOS JUNTOS EN LA LÍNEA ESTRATÉGICA SOCIAL | D8: EDUCACION | E8: Construir 1 Alianza con SENA o instituciones de Educación Superior para oferta educativa
A9: META-008 | B9: 2024257770005 | C9: POR EL SUPATÁ SOÑADO AVANZAMOS JUNTOS EN LA LÍNEA ESTRATÉGICA SOCIAL | D9: EDUCACION | E9: Realizar un (1) convenio anual con el Servicio Nacional de Aprendizaje –SENA-, para la implementación del Programa de Jóvenes Rurales (SENA Emprende Rural)
A10: META-009 | B10: 2024257770005 | C10: POR EL SUPATÁ SOÑADO AVANZAMOS JUNTOS EN LA LÍNEA ESTRATÉGICA SOCIAL | D10: EDUCACION | E10: Desarrollo de programa de mejoramiento de la calidad educativa PROMCE en minimo dos de sus componentes
A11: META-010 | B11: 2024257770006 | C11: POR EL SUPATÁ SOÑADO AVANZAMOS JUNTOS EN LA LÍNEA ESTRATÉGICA SOCIAL | D11: SALUD | E11: Aumentar al 90% la población beneficiada con la Estrategia de APS Municipal
A12: META-011 | B12: 2024257770006 | C12: POR EL SUPATÁ SOÑADO AVANZAMOS JUNTOS EN LA LÍNEA ESTRATÉGICA SOCIAL | D12: SALUD | E12: Implementar un plan de acción de Participación Social en Salud del Departamento
A13: META-012 | B13: 2024257770006 | C13: POR EL SUPATÁ SOÑADO AVANZAMOS JUNTOS EN LA LÍNEA ESTRATÉGICA SOCIAL | D13: SALUD | E13: Gestionar la realizacion de jornadas de salud en la zona rural del municipio para el fortalecimiento de la atencion en el Nivel Primario, aplicacion de tamizajes y acciones de informacion, que incidan en el mantenimiento de la salud y la deteccion oportuna del riego de enfermedades en la poblacion.
... A56: META-055 | B56: 2024257770012 | C56: POR EL SUPATÁ SOÑADO AVANZAMOS JUNTOS EN LA LÍNEA ESTRATÉGICA SOCIAL | D56: POBLACIÓN VULNERABLE - CAPITULO PRIMERA INFANCIA, INFANCIA, ADOLESCENCIA Y JUVENTUD | E56: Realizar cuatro (4) campañas de prevencion de embarazado en mujeres adolescentes
A57: META-056 | B57: 2024257770012 | C57: POR EL SUPATÁ SOÑADO AVANZAMOS JUNTOS EN LA LÍNEA ESTRATÉGICA SOCIAL | D57: POBLACIÓN VULNERABLE - CAPITULO PRIMERA INFANCIA, INFANCIA, ADOLESCENCIA Y JUVENTUD
A58: META-057 | B58: 2024257770012 | C58: POR EL SUPATÁ SOÑADO AVANZAMOS JUNTOS EN LA LÍNEA ESTRATÉGICA SOCIAL | D58: POBLACIÓN VULNERABLE - CAPITULO PRIMERA INFANCIA, INFANCIA, ADOLESCENCIA Y JUVENTUD | E58: Realizar cuatro (4) talleres en reconocimiento de los derechos de niños, niñas y adolescentes
A59: META-058 | B59: 2024257770012 | C59: POR EL SUPATÁ SOÑADO AVANZAMOS JUNTOS EN LA LÍNEA ESTRATÉGICA SOCIAL | D59: POBLACIÓN VULNERABLE - CAPITULO PRIMERA INFANCIA, INFANCIA, ADOLESCENCIA Y JUVENTUD | E59: Realizar cuatro (4) campañas para la proteccioón y prevención del maltrato infantil
A60: META-059 | B60: 2024257770012 | C60: POR EL SUPATÁ SOÑADO AVANZAMOS JUNTOS EN LA LÍNEA ESTRATÉGICA SOCIAL | D60: POBLACIÓN VULNERABLE - CAPITULO PRIMERA INFANCIA, INFANCIA, ADOLESCENCIA Y JUVENTUD | E60: Realizar dotacion en material pedagógico para los programas de atención de primera infancia
A61: META-060 | B61: 2024257770012 | C61: POR EL SUPATÁ SOÑADO AVANZAMOS JUNTOS EN LA LÍNEA ESTRATÉGICA SOCIAL | D61: POBLACIÓN VULNERABLE - CAPITULO PRIMERA INFANCIA, INFANCIA, ADOLESCENCIA Y JUVENTUD | E61: Realizar cuatro (4) campañas para el fortalecimiento familiar en el municipio
A62: META-061 | B62: 2024257770012 | C62: POR EL SUPATÁ SOÑADO AVANZAMOS JUNTOS EN LA LÍNEA ESTRATÉGICA SOCIAL | D62: POBLACIÓN VULNERABLE - CAPITULO PRIMERA INFANCIA, INFANCIA, ADOLESCENCIA Y JUVENTUD | E62: Realizar las acciones necesarias para el aumento de 1 unidad o cupos en la atención del programa “Educación Rural Dispersa”. (VERIFICAR SI ES META DE PRIMERA INFANCIA)
A63: META-062 | B63: 2024257770012 | C63: POR EL SUPATÁ SOÑADO AVANZAMOS JUNTOS EN LA LÍNEA ESTRATÉGICA SOCIAL | D63: POBLACIÓN VULNERABLE - CAPITULO PRIMERA INFANCIA, INFANCIA, ADOLESCENCIA Y JUVENTUD | E63: Realizar campañas anuales para la prevención de la conducta suicida, en niños, niñas, adolescentes y jovenes
A64: META-063 | B64: 2024257770012 | C64: POR EL SUPATÁ SOÑADO AVANZAMOS JUNTOS EN LA LÍNEA ESTRATÉGICA SOCIAL | D64: POBLACIÓN VULNERABLE - CAPITULO PRIMERA INFANCIA, INFANCIA, ADOLESCENCIA Y JUVENTUD | E64: Mantener a 100 niños de 0 a 5 años en establecimientos de educación inicial
A65: META-064 | B65: 2024257770012 | C65: POR EL SUPATÁ SOÑADO AVANZAMOS JUNTOS EN LA LÍNEA ESTRATÉGICA SOCIAL | D65: POBLACIÓN VULNERABLE - CAPITULO PRIMERA INFANCIA, INFANCIA, ADOLESCENCIA Y JUVENTUD | E65: Implementar un programa de apoyo integral a la juventud
A66: META-065 | B66: 2024257770013 | C66: POR EL SUPATÁ SOÑADO AVANZAMOS JUNTOS EN LA LÍNEA ESTRATÉGICA SOCIAL | D66: POBLACIÓN VULNERABLE- CAPITULO MUJER Y GENERO | E66: Construcción de (1) centro de innovación empresarial casa social de la mujer.
A67: META-066 | B67: 2024257770013 | C67: POR EL SUPATÁ SOÑADO AVANZAMOS JUNTOS EN LA LÍNEA ESTRATÉGICA SOCIAL | D67: POBLACIÓN VULNERABLE- CAPITULO MUJER Y GENERO | E67: Realizar anualmente mecanismos para la articulacion, actualización, reactivación y seguimiento de las actividades del Consejo Consultivo de Mujeres, como instancia de representación de sus necesidades e interés
A68: META-067 | B68: 2024257770014 | C68: POR EL SUPATÁ SOÑADO AVANZAMOS JUNTOS EN LA LÍNEA ESTRATÉGICA SOCIAL | D68: POBLACIÓN VULNERABLE - CAPITULO ADULTO MAYOR | E68: Mentener el Programa Centro Día Urbano y rural para el beneficio
A69: META-068 | B69: 2024257770014 | C69: POR EL SUPATÁ SOÑADO AVANZAMOS JUNTOS EN LA LÍNEA ESTRATÉGICA SOCIAL | D69: POBLACIÓN VULNERABLE - CAPITULO ADULTO MAYOR | E69: Garantizar la atención integral e institucional de adultos mayores con vulnerabilidad social en el centro de bienestar del adulto mayor "Maria Auxiliadora".
... A127: META-126 | B127: 2024257770021 | C127: POR EL SUPATÁ SOÑADO AVANZAMOS JUNTOS EN LA LÍNEA ESTRATÉGICA ECONÓMICA | D127: TRANSPORTE | E127: Realizar 300 metros lineales de señalizacion de vías terciarias y urbanas del municipio.
A128: META-127 | B128: 2024257770021 | E128: Realizar 4 capacitaciones sobre seguridad vial a los actores viales del municipio
A129: META-128 | B129: 2024257770023 | C129: POR EL SUPATÁ SOÑADO AVANZAMOS JUNTOS EN LA LÍNEA ESTRATÉGICA ECONÓMICA | D129: AGROPECUARIO | E129: Apoyo (2) proyectos productivos que me garanticen el uso eficiente en ganaderia y uso del suelo.
A130: META-129 | B130: 2024257770023 | C130: POR EL SUPATÁ SOÑADO AVANZAMOS JUNTOS EN LA LÍNEA ESTRATÉGICA ECONÓMICA | D130: AGROPECUARIO | E130: Realizar 400 visitas técnicas solicitada a los sistemas de producción agricolas
A131: META-130 | B131: 2024257770023 | C131: POR EL SUPATÁ SOÑADO AVANZAMOS JUNTOS EN LA LÍNEA ESTRATÉGICA ECONÓMICA | D131: AGROPECUARIO | E131: Implementar 80 huertas y huertos caseras
A132: META-131 | B132: 2024257770023 | C132: POR EL SUPATÁ SOÑADO AVANZAMOS JUNTOS EN LA LÍNEA ESTRATÉGICA ECONÓMICA | D132: AGROPECUARIO | E132: Apoyo a 20 pequeños productores cafeteros del municipio para aumentar las áreas de siembra, mejorar la capacidad productiva y competitividad, en el cuatrenio
A133: META-132 | B133: 2024257770023 | C133: POR EL SUPATÁ SOÑADO AVANZAMOS JUNTOS EN LA LÍNEA ESTRATÉGICA ECONÓMICA | D133: AGROPECUARIO | E133: Fortalecer el Programa de Mercados Campesinos para aumentar la comercializacion de los productos agropecuarios
A134: META-133 | B134: 2024257770023 | C134: POR EL SUPATÁ SOÑADO AVANZAMOS JUNTOS EN LA LÍNEA ESTRATÉGICA ECONÓMICA | D134: AGROPECUARIO | E134: Apoyar a 20 usuarios en la implementacion de sistemas de producción pecuaria con especies menores.
A135: META-134 | B135: 2024257770023 | C135: POR EL SUPATÁ SOÑADO AVANZAMOS JUNTOS EN LA LÍNEA ESTRATÉGICA ECONÓMICA | D135: AGROPECUARIO | E135: Fortalecer anualmente las asociasiones de productores legalmente constituidas
A136: META-135 | B136: 2024257770024 | C136: POR EL SUPATÁ SOÑADO AVANZAMOS JUNTOS EN LA LÍNEA ESTRATÉGICA ECONÓMICA | D136: AGROPECUARIO | E136: Capacitar a 100 personas que elaboren en fincas ganaderas en normatividad ICA
A137: META-136 | B137: 202500000009592 | C137: POR EL SUPATÁ SOÑADO AVANZAMOS JUNTOS EN LA LÍNEA ESTRATÉGICA ECONÓMICA | D137: AGROPECUARIO | E137: Organizar (4) ferias agropecuarias
A138: META-137 | B138: 202500000008911 | C138: POR EL SUPATÁ SOÑADO AVANZAMOS JUNTOS EN LA LÍNEA ESTRATÉGICA ECONÓMICA | D138: AGROPECUARIO | E138: Realizar 500 procedimientos de esterilización canina y felina con el fin de hacer control de población canina y felina
A139: META-138 | B139: 202500000009564 | C139: POR EL SUPATÁ SOÑADO AVANZAMOS JUNTOS EN LA LÍNEA ESTRATÉGICA ECONÓMICA | D139: AGROPECUARIO | E139: Crear el plan agropecuario municipal
A140: META-139 | B140: 202500000008931 | C140: POR EL SUPATÁ SOÑADO AVANZAMOS JUNTOS EN LA LÍNEA ESTRATÉGICA ECONÓMICA | D140: AGROPECUARIO | E140: Realizar 500 chequeos reproductivos en ganado bovino de los diferentes productores del municipio
... A199: META-198 | B199: 202500000009063 | C199: POR EL SUPATÁ SOÑADO AVANZAMOS JUNTOS EN LA LÍNEA ESTRATÉGICA AMBIENTAL | D199: AMBIENTE | E199: apoyar la implementación anual de los proyectos ambientales escolares PRAES

Sheet SECRETARIAS
A1: COD_SECRETARIA | B1: SECRETARIA
A2: SG | B2: Secretaría General y de Gobierno
A3: SP | B3: Secretaría de Planeación y Obras Públicas
A4: SD | B4: Secretaría de Desarrollo Social y Comunitario
A5: SR | B5: Secretaría de Desarrollo Rural, Medio Ambiente y Competitividad
A6: SH | B6: Secretaría de Hacienda

Sheet LISTAS
A1: AÑOS | B1: ESTADOS | C1: FUENTE_FINANCIACION | D1: TIPO_EVIDENCIA
A2: 2024 | B2: No iniciada | C2: Recursos Propios | D2: Contrato
A3: 2025 | B3: En ejecución | C3: SGP | D3: Acta
B4: Cumplida | C4: Regalías | D4: Informe
C5: ICCU | D5: Foto
C6: CAR | D6: Certificado
C7: Gobernación | D7: Registro/Soporte
C8: Nación/Ministerios | D8: Otro
C9: Cooperación
C10: Mixta

Sheet REGISTRO_AVANCES
A1: AÑO | B1: SECRETARIA | C1: ID_META | D1: BPIM | E1: EJE | F1: SECTOR | G1: META_PRODUCTO | H1: META_PROGRAMADA_AÑO | I1: AVANCE_EJECUTADO_AÑO | J1: %_AVANCE_FISICO | K1: PRESUPUESTO_ASIGNADO | L1: PRESUPUESTO_EJECUTADO | M1: %_EJEC_FINANCIERA | N1: PROYECTO_ASOCIADO | O1: FUENTE_FINANCIACION | P1: ESTADO | Q1: TIPO_EVIDENCIA | R1: EVIDENCIA_ARCHIVO_O_RUTA | S1: OBSERVACIONES | T1: FECHA_REGISTRO | U1: RESPONSABLE
A2: 2024 | B2: Secretaría de Planeación y Obras Públicas | C2: META-117 | D2: =IF($C2="","",INDEX(PLAN_DESARROLLO!$B:$B,MATCH($C2,PLAN_DESARROLLO!$A:$A,0))) -> 2024257770021 | E2: =IF($C2="","",INDEX(PLAN_DESARROLLO!$C:$C,MATCH($C2,PLAN_DESARROLLO!$A:$A,0))) -> POR EL SUPATÁ SOÑADO AVANZAMOS JUNTOS EN LA LÍNEA ESTRATÉGICA ECONÓMICA | F2: =IF($C2="","",INDEX(PLAN_DESARROLLO!$D:$D,MATCH($C2,PLAN_DESARROLLO!$A:$A,0))) -> TRANSPORTE | G2: =IF($C2="","",INDEX(PLAN_DESARROLLO!$E:$E,MATCH($C2,PLAN_DESARROLLO!$A:$A,0))) -> Realizar mantenimiento rutinario de 50 Km de vías rurales del municipio (cuneteando, conformando, afirmado y compactado, según la necesidad) en el cuatrienio | H2: 50 | I2: 120 | J2: =IF(OR($H2="",$I2=""),"",IFERROR($I2/$H2,0)) -> 2.4 | K2: 600000000 | L2: 600000000 | M2: =IF(OR($K2="",$L2=""),"",IFERROR($L2/$K2,0)) -> 1 | N2: contrato de combustible, mantenimiento de la maquinaria, pago de los operarios, e incentivo a las juntas de accion comunal por medio de convenios solidarios | O2: Recursos Propios | P2: Cumplida | Q2: Informe | T2: =IF($A2="","",TODAY()) -> 46059
A3: 2025 | B3: Secretaría de Planeación y Obras Públicas | C3: META-117 | D3: =IF($C3="","",INDEX(PLAN_DESARROLLO!$B:$B,MATCH($C3,PLAN_DESARROLLO!$A:$A,0))) -> 2024257770021 | E3: =IF($C3="","",INDEX(PLAN_DESARROLLO!$C:$C,MATCH($C3,PLAN_DESARROLLO!$A:$A,0))) -> POR EL SUPATÁ SOÑADO AVANZAMOS JUNTOS EN LA LÍNEA ESTRATÉGICA ECONÓMICA | F3: =IF($C3="","",INDEX(PLAN_DESARROLLO!$D:$D,MATCH($C3,PLAN_DESARROLLO!$A:$A,0))) -> TRANSPORTE | G3: =IF($C3="","",INDEX(PLAN_DESARROLLO!$E:$E,MATCH($C3,PLAN_DESARROLLO!$A:$A,0))) -> Realizar mantenimiento rutinario de 50 Km de vías rurales del municipio (cuneteando, conformando, afirmado y compactado, según la necesidad) en el cuatrienio | H3: 50 | I3: 300 | J3: =IF(OR($H3="",$I3=""),"",IFERROR($I3/$H3,0)) -> 6 | K3: 600000000 | L3: 1500000000 | M3: =IF(OR($K3="",$L3=""),"",IFERROR($L3/$K3,0)) -> 2.5 | N3: contrato de combustible, mantenimiento de la maquinaria, pago de los operarios, e incentivo a las juntas de accion comunal por medio de convenios solidarios | O3: Recursos Propios | P3: Cumplida | Q3: Informe | T3: =IF($A3="","",TODAY()) -> 46059
A4: 2024 | B4: Secretaría de Planeación y Obras Públicas | C4: META-118 | D4: =IF($C4="","",INDEX(PLAN_DESARROLLO!$B:$B,MATCH($C4,PLAN_DESARROLLO!$A:$A,0))) -> 2024257770021 | E4: =IF($C4="","",INDEX(PLAN_DESARROLLO!$C:$C,MATCH($C4,PLAN_DESARROLLO!$A:$A,0))) -> POR EL SUPATÁ SOÑADO AVANZAMOS JUNTOS EN LA LÍNEA ESTRATÉGICA ECONÓMICA | F4: =IF($C4="","",INDEX(PLAN_DESARROLLO!$D:$D,MATCH($C4,PLAN_DESARROLLO!$A:$A,0))) -> TRANSPORTE | G4: =IF($C4="","",INDEX(PLAN_DESARROLLO!$E:$E,MATCH($C4,PLAN_DESARROLLO!$A:$A,0))) -> Realizar el mejoramiento, adecuación de vías en la zona rural a través de la construcción de 1.000 ML de placa huellas en concreto o pavimentación, en el cuatrienio | H4: 1000 | I4: 400 | J4: =IF(OR($H4="",$I4=""),"",IFERROR($I4/$H4,0)) -> 0.4 | K4: 600000000 | L4: 300000000 | M4: =IF(OR($K4="",$L4=""),"",IFERROR($L4/$K4,0)) -> 0.5 | N4: convenios solidarios con las juntas de accion comunal | O4: Cooperación | P4: En ejecución | Q4: Otro | T4: =IF($A4="","",TODAY()) -> 46059
A5: 2025 | B5: Secretaría de Planeación y Obras Públicas | C5: META-118 | D5: =IF($C5="","",INDEX(PLAN_DESARROLLO!$B:$B,MATCH($C5,PLAN_DESARROLLO!$A:$A,0))) -> 2024257770021 | E5: =IF($C5="","",INDEX(PLAN_DESARROLLO!$C:$C,MATCH($C5,PLAN_DESARROLLO!$A:$A,0))) -> POR EL SUPATÁ SOÑADO AVANZAMOS JUNTOS EN LA LÍNEA ESTRATÉGICA ECONÓMICA | F5: =IF($C5="","",INDEX(PLAN_DESARROLLO!$D:$D,MATCH($C5,PLAN_DESARROLLO!$A:$A,0))) -> TRANSPORTE | G5: =IF($C5="","",INDEX(PLAN_DESARROLLO!$E:$E,MATCH($C5,PLAN_DESARROLLO!$A:$A,0))) -> Realizar el mejoramiento, adecuación de vías en la zona rural a través de la construcción de 1.000 ML de placa huellas en concreto o pavimentación, en el cuatrienio | H5: 1000 | I5: 2000 | J5: =IF(OR($H5="",$I5=""),"",IFERROR($I5/$H5,0)) -> 2 | K5: 600000000 | L5: 2000000000 | M5: =IF(OR($K5="",$L5=""),"",IFERROR($L5/$K5,0)) -> 3.3333333 | N5: convenios interadministrativos, con la gobernacion de cundinamarca | O5: Gobernación | P5: Cumplida | Q5: Informe | T5: =IF($A5="","",TODAY()) -> 46059
A6: 2024 | B6: Secretaría de Planeación y Obras Públicas | C6: META-119 | D6: =IF($C6="","",INDEX(PLAN_DESARROLLO!$B:$B,MATCH($C6,PLAN_DESARROLLO!$A:$A,0))) -> 2024257770021 | E6: =IF($C6="","",INDEX(PLAN_DESARROLLO!$C:$C,MATCH($C6,PLAN_DESARROLLO!$A:$A,0))) -> POR EL SUPATÁ SOÑADO AVANZAMOS JUNTOS EN LA LÍNEA ESTRATÉGICA ECONÓMICA | F6: =IF($C6="","",INDEX(PLAN_DESARROLLO!$D:$D,MATCH($C6,PLAN_DESARROLLO!$A:$A,0))) -> TRANSPORTE | G6: =IF($C6="","",INDEX(PLAN_DESARROLLO!$E:$E,MATCH($C6,PLAN_DESARROLLO!$A:$A,0))) -> Construir 10 obras de arte para el mantenimiento y mejoramiento de la red terciaria del municipio, durante el cuatrienio | H6: 5 | I6: 2 | J6: =IF(OR($H6="",$I6=""),"",IFERROR($I6/$H6,0)) -> 0.4 | K6: 150000000 | L6: 150000000 | M6: =IF(OR($K6="",$L6=""),"",IFERROR($L6/$K6,0)) -> 1 | N6: arreglos y mantenimiento a la alcantarillas y arreglo de pasos rurales en conjunto con las juntas de accion comunal | O6: SGP | P6: En ejecución | Q6: Informe
A7: 2025 | B7: Secretaría de Planeación y Obras Públicas | C7: META-119 | D7: =IF($C7="","",INDEX(PLAN_DESARROLLO!$B:$B,MATCH($C7,PLAN_DESARROLLO!$A:$A,0))) -> 2024257770021 | E7: =IF($C7="","",INDEX(PLAN_DESARROLLO!$C:$C,MATCH($C7,PLAN_DESARROLLO!$A:$A,0))) -> POR EL SUPATÁ SOÑADO AVANZAMOS JUNTOS EN LA LÍNEA ESTRATÉGICA ECONÓMICA | F7: =IF($C7="","",INDEX(PLAN_DESARROLLO!$D:$D,MATCH($C7,PLAN_DESARROLLO!$A:$A,0))) -> TRANSPORTE | G7: =IF($C7="","",INDEX(PLAN_DESARROLLO!$E:$E,MATCH($C7,PLAN_DESARROLLO!$A:$A,0))) -> Construir 10 obras de arte para el mantenimiento y mejoramiento de la red terciaria del municipio, durante el cuatrienio | H7: 5 | I7: 5 | J7: =IF(OR($H7="",$I7=""),"",IFERROR($I7/$H7,0)) -> 1 | K7: 300000000 | L7: 300000000 | M7: =IF(OR($K7="",$L7=""),"",IFERROR($L7/$K7,0)) -> 1 | N7: arreglos y mantenimiento a la alcantarillas y arreglo de pasos rurales en conjunto con las juntas de accion comunal | O7: SGP | P7: Cumplida | Q7: Informe | T7: =IF($A7="","",TODAY()) -> 46059
A8: 2024 | B8: Secretaría de Planeación y Obras Públicas | C8: META-046 | D8: =IF($C8="","",INDEX(PLAN_DESARROLLO!$B:$B,MATCH($C8,PLAN_DESARROLLO!$A:$A,0))) -> 2024257770010 | E8: =IF($C8="","",INDEX(PLAN_DESARROLLO!$C:$C,MATCH($C8,PLAN_DESARROLLO!$A:$A,0))) -> POR EL SUPATÁ SOÑADO AVANZAMOS JUNTOS EN LA LÍNEA ESTRATÉGICA SOCIAL | F8: =IF($C8="","",INDEX(PLAN_DESARROLLO!$D:$D,MATCH($C8,PLAN_DESARROLLO!$A:$A,0))) -> RECREACION Y DEPROTE | G8: =IF($C8="","",INDEX(PLAN_DESARROLLO!$E:$E,MATCH($C8,PLAN_DESARROLLO!$A:$A,0))) -> Realizar 2 estudios y diseños para infraestructura deportiva y recreativa en el municipio | H8: 2 | I8: 0 | J8: =IF(OR($H8="",$I8=""),"",IFERROR($I8/$H8,0)) -> 0 | K8: 0 | L8: 0 | M8: =IF(OR($K8="",$L8=""),"",IFERROR($L8/$K8,0)) -> 0 | N8: en proceso de estudios y diseños | O8: Recursos Propios | P8: No iniciada | Q8: Otro | T8: =IF($A8="","",TODAY()) -> 46059
A9: 2025 | B9: Secretaría de Planeación y Obras Públicas | C9: META-046 | D9: =IF($C9="","",INDEX(PLAN_DESARROLLO!$B:$B,MATCH($C9,PLAN_DESARROLLO!$A:$A,0))) -> 2024257770010 | E9: =IF($C9="","",INDEX(PLAN_DESARROLLO!$C:$C,MATCH($C9,PLAN_DESARROLLO!$A:$A,0))) -> POR EL SUPATÁ SOÑADO AVANZAMOS JUNTOS EN LA LÍNEA ESTRATÉGICA SOCIAL | F9: =IF($C9="","",INDEX(PLAN_DESARROLLO!$D:$D,MATCH($C9,PLAN_DESARROLLO!$A:$A,0))) -> RECREACION Y DEPROTE | G9: =IF($C9="","",INDEX(PLAN_DESARROLLO!$E:$E,MATCH($C9,PLAN_DESARROLLO!$A:$A,0))) -> Realizar 2 estudios y diseños para infraestructura deportiva y recreativa en el municipio | H9: 2 | I9: 2 | J9: =IF(OR($H9="",$I9=""),"",IFERROR($I9/$H9,0)) -> 1 | K9: 0 | L9: 0 | M9: =IF(OR($K9="",$L9=""),"",IFERROR($L9/$K9,0)) -> 0 | N9: estudios y diseños realizados | O9: Recursos Propios | P9: En ejecución | Q9: Informe | T9: =IF($A9="","",TODAY()) -> 46059
A10: 2024 | B10: Secretaría de Planeación y Obras Públicas | C10: META-079 | D10: =IF($C10="","",INDEX(PLAN_DESARROLLO!$B:$B,MATCH($C10,PLAN_DESARROLLO!$A:$A,0))) -> 2024257770016 | E10: =IF($C10="","",INDEX(PLAN_DESARROLLO!$C:$C,MATCH($C10,PLAN_DESARROLLO!$A:$A,0))) -> POR EL SUPATÁ SOÑADO AVANZAMOS JUNTOS EN LA LÍNEA ESTRATÉGICA SOCIAL | F10: =IF($C10="","",INDEX(PLAN_DESARROLLO!$D:$D,MATCH($C10,PLAN_DESARROLLO!$A:$A,0))) -> VIVIENDA, CIUDAD Y TERRITORIO | G10: =IF($C10="","",INDEX(PLAN_DESARROLLO!$E:$E,MATCH($C10,PLAN_DESARROLLO!$A:$A,0))) -> Fortalecer administrativa y logística anualmente el Consejo Territorial de Planeación para su funcionamiento. (pendiente fortalecimiento institucional cambio de sector) | H10: 1 | I10: 1 | J10: =IF(OR($H10="",$I10=""),"",IFERROR($I10/$H10,0)) -> 1 | K10: 0 | L10: 0 | M10: =IF(OR($K10="",$L10=""),"",IFERROR($L10/$K10,0)) -> 0 | N10: se envia a los miembros del comité informacion sobre capacitaciones | O10: Cooperación | P10: En ejecución | Q10: Otro | T10: =IF($A10="","",TODAY()) -> 46059
A11: 2025 | B11: Secretaría de Planeación y Obras Públicas | C11: META-079 | D11: =IF($C11="","",INDEX(PLAN_DESARROLLO!$B:$B,MATCH($C11,PLAN_DESARROLLO!$A:$A,0))) -> 2024257770016 | E11: =IF($C11="","",INDEX(PLAN_DESARROLLO!$C:$C,MATCH($C11,PLAN_DESARROLLO!$A:$A,0))) -> POR EL SUPATÁ SOÑADO AVANZAMOS JUNTOS EN LA LÍNEA ESTRATÉGICA SOCIAL | F11: =IF($C11="","",INDEX(PLAN_DESARROLLO!$D:$D,MATCH($C11,PLAN_DESARROLLO!$A:$A,0))) -> VIVIENDA, CIUDAD Y TERRITORIO | G11: =IF($C11="","",INDEX(PLAN_DESARROLLO!$E:$E,MATCH($C11,PLAN_DESARROLLO!$A:$A,0))) -> Fortalecer administrativa y logística anualmente el Consejo Territorial de Planeación para su funcionamiento. (pendiente fortalecimiento institucional cambio de sector) | H11: 1 | I11: 1 | J11: =IF(OR($H11="",$I11=""),"",IFERROR($I11/$H11,0)) -> 1 | K11: 0 | L11: 0 | M11: =IF(OR($K11="",$L11=""),"",IFERROR($L11/$K11,0)) -> 0 | N11: se envia a los miembros del comité informacion sobre capacitaciones | O11: Cooperación | P11: En ejecución | Q11: Otro | T11: =IF($A11="","",TODAY()) -> 46059
A12: 2024 | B12: Secretaría de Planeación y Obras Públicas | C12: META-080 | D12: =IF($C12="","",INDEX(PLAN_DESARROLLO!$B:$B,MATCH($C12,PLAN_DESARROLLO!$A:$A,0))) -> 2024257770016 | E12: =IF($C12="","",INDEX(PLAN_DESARROLLO!$C:$C,MATCH($C12,PLAN_DESARROLLO!$A:$A,0))) -> POR EL SUPATÁ SOÑADO AVANZAMOS JUNTOS EN LA LÍNEA ESTRATÉGICA SOCIAL | F12: =IF($C12="","",INDEX(PLAN_DESARROLLO!$D:$D,MATCH($C12,PLAN_DESARROLLO!$A:$A,0))) -> VIVIENDA, CIUDAD Y TERRITORIO | G12: =IF($C12="","",INDEX(PLAN_DESARROLLO!$E:$E,MATCH($C12,PLAN_DESARROLLO!$A:$A,0))) -> Adecuación y mantenimiento de la plaza de ferias municipal | H12: 1 | I12: 0 | J12: =IF(OR($H12="",$I12=""),"",IFERROR($I12/$H12,0)) -> 0 | K12: 0 | L12: 0 | M12: =IF(OR($K12="",$L12=""),"",IFERROR($L12/$K12,0)) -> 0 | N12: en proceso de estudios y diseños | O12: Regalías | P12: No iniciada | Q12: Otro | T12: =IF($A12="","",TODAY()) -> 46059
A13: 2025 | B13: Secretaría de Planeación y Obras Públicas | C13: META-080 | D13: =IF($C13="","",INDEX(PLAN_DESARROLLO!$B:$B,MATCH($C13,PLAN_DESARROLLO!$A:$A,0))) -> 2024257770016 | E13: =IF($C13="","",INDEX(PLAN_DESARROLLO!$C:$C,MATCH($C13,PLAN_DESARROLLO!$A:$A,0))) -> POR EL SUPATÁ SOÑADO AVANZAMOS JUNTOS EN LA LÍNEA ESTRATÉGICA SOCIAL | F13: =IF($C13="","",INDEX(PLAN_DESARROLLO!$D:$D,MATCH($C13,PLAN_DESARROLLO!$A:$A,0))) -> VIVIENDA, CIUDAD Y TERRITORIO | G13: =IF($C13="","",INDEX(PLAN_DESARROLLO!$E:$E,MATCH($C13,PLAN_DESARROLLO!$A:$A,0))) -> Adecuación y mantenimiento de la plaza de ferias municipal | H13: 1 | I13: 1 | J13: =IF(OR($H13="",$I13=""),"",IFERROR($I13/$H13,0)) -> 1 | K13: 1700000000 | L13: 1700000000 | M13: =IF(OR($K13="",$L13=""),"",IFERROR($L13/$K13,0)) -> 1 | N13: estudios y diseños avalados por regalias y en proceso de cadjudicación | O13: Regalías | P13: En ejecución | Q13: Informe | T13: =IF($A13="","",TODAY()) -> 46059
A14: 2024 | B14: Secretaría de Planeación y Obras Públicas | C14: META-081 | D14: =IF($C14="","",INDEX(PLAN_DESARROLLO!$B:$B,MATCH($C14,PLAN_DESARROLLO!$A:$A,0))) -> 2024257770016 | E14: =IF($C14="","",INDEX(PLAN_DESARROLLO!$C:$C,MATCH($C14,PLAN_DESARROLLO!$A:$A,0))) -> POR EL SUPATÁ SOÑADO AVANZAMOS JUNTOS EN LA LÍNEA ESTRATÉGICA SOCIAL | F14: =IF($C14="","",INDEX(PLAN_DESARROLLO!$D:$D,MATCH($C14,PLAN_DESARROLLO!$A:$A,0))) -> VIVIENDA, CIUDAD Y TERRITORIO | G14: =IF($C14="","",INDEX(PLAN_DESARROLLO!$E:$E,MATCH($C14,PLAN_DESARROLLO!$A:$A,0))) -> Realizar 2 mantenimientos a la plaza de mercado | H14: 2 | I14: 0 | J14: =IF(OR($H14="",$I14=""),"",IFERROR($I14/$H14,0)) -> 0 | K14: 0 | L14: 0 | M14: =IF(OR($K14="",$L14=""),"",IFERROR($L14/$K14,0)) -> 0 | N14: en proceso de estudios | O14: Recursos Propios | P14: No iniciada | Q14: Informe | T14: =IF($A14="","",TODAY()) -> 46059
A15: 2025 | B15: Secretaría de Planeación y Obras Públicas | C15: META-081 | D15: =IF($C15="","",INDEX(PLAN_DESARROLLO!$B:$B,MATCH($C15,PLAN_DESARROLLO!$A:$A,0))) -> 2024257770016 | E15: =IF($C15="","",INDEX(PLAN_DESARROLLO!$C:$C,MATCH($C15,PLAN_DESARROLLO!$A:$A,0))) -> POR EL SUPATÁ SOÑADO AVANZAMOS JUNTOS EN LA LÍNEA ESTRATÉGICA SOCIAL | F15: =IF($C15="","",INDEX(PLAN_DESARROLLO!$D:$D,MATCH($C15,PLAN_DESARROLLO!$A:$A,0))) -> VIVIENDA, CIUDAD Y TERRITORIO | G15: =IF($C15="","",INDEX(PLAN_DESARROLLO!$E:$E,MATCH($C15,PLAN_DESARROLLO!$A:$A,0))) -> Realizar 2 mantenimientos a la plaza de mercado | H15: 2 | I15: 0 | J15: =IF(OR($H15="",$I15=""),"",IFERROR($I15/$H15,0)) -> 0 | K15: 0 | L15: 0 | M15: =IF(OR($K15="",$L15=""),"",IFERROR($L15/$K15,0)) -> 0 | N15: en proceso de estudios | O15: Recursos Propios | P15: No iniciada | Q15: Informe | T15: =IF($A15="","",TODAY()) -> 46059
A16: 2024 | B16: Secretaría de Planeación y Obras Públicas | C16: META-082 | D16: =IF($C16="","",INDEX(PLAN_DESARROLLO!$B:$B,MATCH($C16,PLAN_DESARROLLO!$A:$A,0))) -> 2024257770016 | E16: =IF($C16="","",INDEX(PLAN_DESARROLLO!$C:$C,MATCH($C16,PLAN_DESARROLLO!$A:$A,0))) -> POR EL SUPATÁ SOÑADO AVANZAMOS JUNTOS EN LA LÍNEA ESTRATÉGICA SOCIAL | F16: =IF($C16="","",INDEX(PLAN_DESARROLLO!$D:$D,MATCH($C16,PLAN_DESARROLLO!$A:$A,0))) -> VIVIENDA, CIUDAD Y TERRITORIO | G16: =IF($C16="","",INDEX(PLAN_DESARROLLO!$E:$E,MATCH($C16,PLAN_DESARROLLO!$A:$A,0))) -> Implementar el programa anual de Banco de Materiales que une esfuerzos entre la administración municipal y la comunidad para la realización de obras necesarias y de gran impacto social en barrios y veredas. | H16: 1 | I16: 1 | J16: =IF(OR($H16="",$I16=""),"",IFERROR($I16/$H16,0)) -> 1 | K16: 30000000 | L16: 30000000 | M16: =IF(OR($K16="",$L16=""),"",IFERROR($L16/$K16,0)) -> 1 | N16: se contrato el proceso de banco de materiales | O16: Recursos Propios | P16: Cumplida | Q16: Informe | T16: =IF($A16="","",TODAY()) -> 46059
A17: 2025 | B17: Secretaría de Planeación y Obras Públicas | C17: META-082 | D17: =IF($C17="","",INDEX(PLAN_DESARROLLO!$B:$B,MATCH($C17,PLAN_DESARROLLO!$A:$A,0))) -> 2024257770016 | E17: =IF($C17="","",INDEX(PLAN_DESARROLLO!$C:$C,MATCH($C17,PLAN_DESARROLLO!$A:$A,0))) -> POR EL SUPATÁ SOÑADO AVANZAMOS JUNTOS EN LA LÍNEA ESTRATÉGICA SOCIAL | F17: =IF($C17="","",INDEX(PLAN_DESARROLLO!$D:$D,MATCH($C17,PLAN_DESARROLLO!$A:$A,0))) -> VIVIENDA, CIUDAD Y TERRITORIO | G17: =IF($C17="","",INDEX(PLAN_DESARROLLO!$E:$E,MATCH($C17,PLAN_DESARROLLO!$A:$A,0))) -> Implementar el programa anual de Banco de Materiales que une esfuerzos entre la administración municipal y la comunidad para la realización de obras necesarias y de gran impacto social en barrios y veredas. | H17: 1 | I17: 1 | J17: =IF(OR($H17="",$I17=""),"",IFERROR($I17/$H17,0)) -> 1 | K17: 46000000 | L17: 46000000 | M17: =IF(OR($K17="",$L17=""),"",IFERROR($L17/$K17,0)) -> 1 | N17: se contrato el proceso de banco de materiales y elementos de ferreteria | O17: Recursos Propios | P17: Cumplida | Q17: Informe | T17: =IF($A17="","",TODAY()) -> 46059
A18: 2024 | B18: Secretaría de Planeación y Obras Públicas | C18: META-083 | D18: =IF($C18="","",INDEX(PLAN_DESARROLLO!$B:$B,MATCH($C18,PLAN_DESARROLLO!$A:$A,0))) -> 2024257770016 | E18: =IF($C18="","",INDEX(PLAN_DESARROLLO!$C:$C,MATCH($C18,PLAN_DESARROLLO!$A:$A,0))) -> POR EL SUPATÁ SOÑADO AVANZAMOS JUNTOS EN LA LÍNEA ESTRATÉGICA SOCIAL | F18: =IF($C18="","",INDEX(PLAN_DESARROLLO!$D:$D,MATCH($C18,PLAN_DESARROLLO!$A:$A,0))) -> VIVIENDA, CIUDAD Y TERRITORIO | G18: =IF($C18="","",INDEX(PLAN_DESARROLLO!$E:$E,MATCH($C18,PLAN_DESARROLLO!$A:$A,0))) -> Implementar un programa de mantenimiento de espacio público, zonas verdes y parques del municipio | H18: 1 | I18: 1 | J18: =IF(OR($H18="",$I18=""),"",IFERROR($I18/$H18,0)) -> 1 | K18: 50000000 | L18: 50000000 | M18: =IF(OR($K18="",$L18=""),"",IFERROR($L18/$K18,0)) -> 1 | N18: se realizan mantenimientos, pero tambien la contratacion del personal para el cuidado y preservacion de estos espacios | O18: SGP | P18: Cumplida | Q18: Informe | T18: =IF($A18="","",TODAY()) -> 46059
... A23: 2025 | B23: Secretaría de Planeación y Obras Públicas | C23: META-085 | D23: =IF($C23="","",INDEX(PLAN_DESARROLLO!$B:$B,MATCH($C23,PLAN_DESARROLLO!$A:$A,0))) -> 2024257770016 | E23: =IF($C23="","",INDEX(PLAN_DESARROLLO!$C:$C,MATCH($C23,PLAN_DESARROLLO!$A:$A,0))) -> POR EL SUPATÁ SOÑADO AVANZAMOS JUNTOS EN LA LÍNEA ESTRATÉGICA SOCIAL | F23: =IF($C23="","",INDEX(PLAN_DESARROLLO!$D:$D,MATCH($C23,PLAN_DESARROLLO!$A:$A,0))) -> VIVIENDA, CIUDAD Y TERRITORIO | G23: =IF($C23="","",INDEX(PLAN_DESARROLLO!$E:$E,MATCH($C23,PLAN_DESARROLLO!$A:$A,0))) -> Estudios y diseños para la construcción de la casa de gobierno | H23: 1 | I23: 1 | J23: =IF(OR($H23="",$I23=""),"",IFERROR($I23/$H23,0)) -> 1 | K23: 0 | L23: 0 | M23: =IF(OR($K23="",$L23=""),"",IFERROR($L23/$K23,0)) -> 0 | N23: en proceso de adjudicacion luego de ser aprobados los estudios y diseños, en convenio entre la gobernacion de cundinamarca y los fondos por regalias | O23: Mixta | P23: Cumplida | Q23: Informe | T23: =IF($A23="","",TODAY()) -> 46059
A24: 2024 | B24: Secretaría de Planeación y Obras Públicas | C24: META-086 | D24: =IF($C24="","",INDEX(PLAN_DESARROLLO!$B:$B,MATCH($C24,PLAN_DESARROLLO!$A:$A,0))) -> 2024257770017 | E24: =IF($C24="","",INDEX(PLAN_DESARROLLO!$C:$C,MATCH($C24,PLAN_DESARROLLO!$A:$A,0))) -> POR EL SUPATÁ SOÑADO AVANZAMOS JUNTOS EN LA LÍNEA ESTRATÉGICA SOCIAL | F24: =IF($C24="","",INDEX(PLAN_DESARROLLO!$D:$D,MATCH($C24,PLAN_DESARROLLO!$A:$A,0))) -> A.P.S.B | G24: =IF($C24="","",INDEX(PLAN_DESARROLLO!$E:$E,MATCH($C24,PLAN_DESARROLLO!$A:$A,0))) -> Realizar 1 optimizacion a la planta de tratamiento de agua potable | H24: 0 | I24: 0 | J24: =IF(OR($H24="",$I24=""),"",IFERROR($I24/$H24,0)) -> 0 | K24: 0 | L24: 0 | M24: =IF(OR($K24="",$L24=""),"",IFERROR($L24/$K24,0)) -> 0 | T24: =IF($A24="","",TODAY()) -> 46059
A25: 2025 | B25: Secretaría de Planeación y Obras Públicas | C25: META-086 | D25: =IF($C25="","",INDEX(PLAN_DESARROLLO!$B:$B,MATCH($C25,PLAN_DESARROLLO!$A:$A,0))) -> 2024257770017 | E25: =IF($C25="","",INDEX(PLAN_DESARROLLO!$C:$C,MATCH($C25,PLAN_DESARROLLO!$A:$A,0))) -> POR EL SUPATÁ SOÑADO AVANZAMOS JUNTOS EN LA LÍNEA ESTRATÉGICA SOCIAL | F25: =IF($C25="","",INDEX(PLAN_DESARROLLO!$D:$D,MATCH($C25,PLAN_DESARROLLO!$A:$A,0))) -> A.P.S.B | G25: =IF($C25="","",INDEX(PLAN_DESARROLLO!$E:$E,MATCH($C25,PLAN_DESARROLLO!$A:$A,0))) -> Realizar 1 optimizacion a la planta de tratamiento de agua potable | H25: 1 | I25: 1 | J25: =IF(OR($H25="",$I25=""),"",IFERROR($I25/$H25,0)) -> 1 | K25: 57470328 | L25: 57470328 | M25: =IF(OR($K25="",$L25=""),"",IFERROR($L25/$K25,0)) -> 1 | N25: Contrato de Obra Pública No. 004-2025 Adecuación y mejoramiento de la planta de tratamiento de agua potable del Municipio de Supatá Cundinamarca | O25: SGP - APSB | P25: En ejecución | Q25: Informe | T25: =IF($A25="","",TODAY()) -> 46059
A26: 2024 | B26: Secretaría de Planeación y Obras Públicas | C26: META-087 | D26: =IF($C26="","",INDEX(PLAN_DESARROLLO!$B:$B,MATCH($C26,PLAN_DESARROLLO!$A:$A,0))) -> 2024257770017 | E26: =IF($C26="","",INDEX(PLAN_DESARROLLO!$C:$C,MATCH($C26,PLAN_DESARROLLO!$A:$A,0))) -> POR EL SUPATÁ SOÑADO AVANZAMOS JUNTOS EN LA LÍNEA ESTRATÉGICA SOCIAL | F26: =IF($C26="","",INDEX(PLAN_DESARROLLO!$D:$D,MATCH($C26,PLAN_DESARROLLO!$A:$A,0))) -> A.P.S.B | G26: =IF($C26="","",INDEX(PLAN_DESARROLLO!$E:$E,MATCH($C26,PLAN_DESARROLLO!$A:$A,0))) -> Otorgar anualmente subsidios a los usuarios de los servicios de acueducto, de los estratos 1, 2 y 3 del área urbana,en el cuatrienio | H26: 1 | I26: 1 | J26: =IF(OR($H26="",$I26=""),"",IFERROR($I26/$H26,0)) -> 1 | K26: 22731829 | L26: 22731829 | M26: =IF(OR($K26="",$L26=""),"",IFERROR($L26/$K26,0)) -> 1 | N26: Pago de subsidios del servicio de Acueducto | O26: SGP - APSB | P26: Cumplida | Q26: Certificación | T26: =IF($A26="","",TODAY()) -> 46059
A27: 2025 | B27: Secretaría de Planeación y Obras Públicas | C27: META-087 | D27: =IF($C27="","",INDEX(PLAN_DESARROLLO!$B:$B,MATCH($C27,PLAN_DESARROLLO!$A:$A,0))) -> 2024257770017 | E27: =IF($C27="","",INDEX(PLAN_DESARROLLO!$C:$C,MATCH($C27,PLAN_DESARROLLO!$A:$A,0))) -> POR EL SUPATÁ SOÑADO AVANZAMOS JUNTOS EN LA LÍNEA ESTRATÉGICA SOCIAL | F27: =IF($C27="","",INDEX(PLAN_DESARROLLO!$D:$D,MATCH($C27,PLAN_DESARROLLO!$A:$A,0))) -> A.P.S.B | G27: =IF($C27="","",INDEX(PLAN_DESARROLLO!$E:$E,MATCH($C27,PLAN_DESARROLLO!$A:$A,0))) -> Otorgar anualmente subsidios a los usuarios de los servicios de acueducto, de los estratos 1, 2 y 3 del área urbana,en el cuatrienio | H27: 1 | I27: 1 | J27: =IF(OR($H27="",$I27=""),"",IFERROR($I27/$H27,0)) -> 1 | K27: 25162536 | L27: 25162536 | M27: =IF(OR($K27="",$L27=""),"",IFERROR($L27/$K27,0)) -> 1 | N27: Pago de subsidios del servicio de Acueducto | O27: SGP - APSB | P27: Cumplida | Q27: Certificación | T27: =IF($A27="","",TODAY()) -> 46059
A28: 2024 | B28: Secretaría de Planeación y Obras Públicas | C28: META-088 | D28: =IF($C28="","",INDEX(PLAN_DESARROLLO!$B:$B,MATCH($C28,PLAN_DESARROLLO!$A:$A,0))) -> 2024257770017 | E28: =IF($C28="","",INDEX(PLAN_DESARROLLO!$C:$C,MATCH($C28,PLAN_DESARROLLO!$A:$A,0))) -> POR EL SUPATÁ SOÑADO AVANZAMOS JUNTOS EN LA LÍNEA ESTRATÉGICA SOCIAL | F28: =IF($C28="","",INDEX(PLAN_DESARROLLO!$D:$D,MATCH($C28,PLAN_DESARROLLO!$A:$A,0))) -> A.P.S.B | G28: =IF($C28="","",INDEX(PLAN_DESARROLLO!$E:$E,MATCH($C28,PLAN_DESARROLLO!$A:$A,0))) -> Realizar optimizaciones a los acueductos veredales | H28: 1 | I28: 0 | J28: =IF(OR($H28="",$I28=""),"",IFERROR($I28/$H28,0)) -> 0 | K28: 0 | L28: 0 | M28: =IF(OR($K28="",$L28=""),"",IFERROR($L28/$K28,0)) -> 0 | T28: =IF($A28="","",TODAY()) -> 46059
A29: 2025 | B29: Secretaría de Planeación y Obras Públicas | C29: META-088 | D29: =IF($C29="","",INDEX(PLAN_DESARROLLO!$B:$B,MATCH($C29,PLAN_DESARROLLO!$A:$A,0))) -> 2024257770017 | E29: =IF($C29="","",INDEX(PLAN_DESARROLLO!$C:$C,MATCH($C29,PLAN_DESARROLLO!$A:$A,0))) -> POR EL SUPATÁ SOÑADO AVANZAMOS JUNTOS EN LA LÍNEA ESTRATÉGICA SOCIAL | F29: =IF($C29="","",INDEX(PLAN_DESARROLLO!$D:$D,MATCH($C29,PLAN_DESARROLLO!$A:$A,0))) -> A.P.S.B | G29: =IF($C29="","",INDEX(PLAN_DESARROLLO!$E:$E,MATCH($C29,PLAN_DESARROLLO!$A:$A,0))) -> Realizar optimizaciones a los acueductos veredales | H29: 1 | I29: 2 | J29: =IF(OR($H29="",$I29=""),"",IFERROR($I29/$H29,0)) -> 2 | K29: =98381800+127531800 -> 225913600 | L29: =98381800+127531800 -> 225913600 | M29: =IF(OR($K29="",$L29=""),"",IFERROR($L29/$K29,0)) -> 1 | N29: Convenio de Asociacion No EPC-PDA-CAS-024 y EPC-PDA-CAS-021 entre Empresas Publicas de Cundinamarca - EPC y las asociaciones de acueudcto de Cabrera y el Acueducto Regional de las veredas Santa Rosa, Providencia, Cristales y Mesitas, para el fortalecimiento institucional, comercial, técnico y financiero. | O29: SGP - APSB PDA | P29: Cumplida | Q29: Informe | T29: =IF($A29="","",TODAY()) -> 46059
A30: 2024 | B30: Secretaría de Planeación y Obras Públicas | C30: META-089 | D30: =IF($C30="","",INDEX(PLAN_DESARROLLO!$B:$B,MATCH($C30,PLAN_DESARROLLO!$A:$A,0))) -> 2024257770017 | E30: =IF($C30="","",INDEX(PLAN_DESARROLLO!$C:$C,MATCH($C30,PLAN_DESARROLLO!$A:$A,0))) -> POR EL SUPATÁ SOÑADO AVANZAMOS JUNTOS EN LA LÍNEA ESTRATÉGICA SOCIAL | F30: =IF($C30="","",INDEX(PLAN_DESARROLLO!$D:$D,MATCH($C30,PLAN_DESARROLLO!$A:$A,0))) -> A.P.S.B | G30: =IF($C30="","",INDEX(PLAN_DESARROLLO!$E:$E,MATCH($C30,PLAN_DESARROLLO!$A:$A,0))) -> Realizar la construcción de 200 metros lineales de red de acueducto en el municipio | H30: 0 | I30: 0 | J30: =IF(OR($H30="",$I30=""),"",IFERROR($I30/$H30,0)) -> 0 | K30: 0 | L30: 0 | M30: =IF(OR($K30="",$L30=""),"",IFERROR($L30/$K30,0)) -> 0 | T30: =IF($A30="","",TODAY()) -> 46059
A31: 2025 | B31: Secretaría de Planeación y Obras Públicas | C31: META-089 | D31: =IF($C31="","",INDEX(PLAN_DESARROLLO!$B:$B,MATCH($C31,PLAN_DESARROLLO!$A:$A,0))) -> 2024257770017 | E31: =IF($C31="","",INDEX(PLAN_DESARROLLO!$C:$C,MATCH($C31,PLAN_DESARROLLO!$A:$A,0))) -> POR EL SUPATÁ SOÑADO AVANZAMOS JUNTOS EN LA LÍNEA ESTRATÉGICA SOCIAL | F31: =IF($C31="","",INDEX(PLAN_DESARROLLO!$D:$D,MATCH($C31,PLAN_DESARROLLO!$A:$A,0))) -> A.P.S.B | G31: =IF($C31="","",INDEX(PLAN_DESARROLLO!$E:$E,MATCH($C31,PLAN_DESARROLLO!$A:$A,0))) -> Realizar la construcción de 200 metros lineales de red de acueducto en el municipio | H31: 0 | I31: 0 | J31: =IF(OR($H31="",$I31=""),"",IFERROR($I31/$H31,0)) -> 0 | K31: 0 | L31: 0 | M31: =IF(OR($K31="",$L31=""),"",IFERROR($L31/$K31,0)) -> 0 | T31: =IF($A31="","",TODAY()) -> 46059
A32: 2024 | B32: Secretaría de Planeación y Obras Públicas | C32: META-090 | D32: =IF($C32="","",INDEX(PLAN_DESARROLLO!$B:$B,MATCH($C32,PLAN_DESARROLLO!$A:$A,0))) -> 2024257770017 | E32: =IF($C32="","",INDEX(PLAN_DESARROLLO!$C:$C,MATCH($C32,PLAN_DESARROLLO!$A:$A,0))) -> POR EL SUPATÁ SOÑADO AVANZAMOS JUNTOS EN LA LÍNEA ESTRATÉGICA SOCIAL | F32: =IF($C32="","",INDEX(PLAN_DESARROLLO!$D:$D,MATCH($C32,PLAN_DESARROLLO!$A:$A,0))) -> A.P.S.B | G32: =IF($C32="","",INDEX(PLAN_DESARROLLO!$E:$E,MATCH($C32,PLAN_DESARROLLO!$A:$A,0))) -> Transferir anualmente al Plan Departamental de Aguas -PDA- los recursos comprometidos a través de Acuerdo Municipal en el cuatrienio. | H32: 1 | I32: 1 | J32: =IF(OR($H32="",$I32=""),"",IFERROR($I32/$H32,0)) -> 1 | K32: 442578049 | L32: 442578049 | M32: =IF(OR($K32="",$L32=""),"",IFERROR($L32/$K32,0)) -> 1 | N32: Transferencia del 60% del toral de los recursos de APSB al PDA vigencia 2024 | O32: SGP - APSB | P32: Cumplida | Q32: Certificación | T32: =IF($A32="","",TODAY()) -> 46059
A33: 2025 | B33: Secretaría de Planeación y Obras Públicas | C33: META-090 | D33: =IF($C33="","",INDEX(PLAN_DESARROLLO!$B:$B,MATCH($C33,PLAN_DESARROLLO!$A:$A,0))) -> 2024257770017 | E33: =IF($C33="","",INDEX(PLAN_DESARROLLO!$C:$C,MATCH($C33,PLAN_DESARROLLO!$A:$A,0))) -> POR EL SUPATÁ SOÑADO AVANZAMOS JUNTOS EN LA LÍNEA ESTRATÉGICA SOCIAL | F33: =IF($C33="","",INDEX(PLAN_DESARROLLO!$D:$D,MATCH($C33,PLAN_DESARROLLO!$A:$A,0))) -> A.P.S.B | G33: =IF($C33="","",INDEX(PLAN_DESARROLLO!$E:$E,MATCH($C33,PLAN_DESARROLLO!$A:$A,0))) -> Transferir anualmente al Plan Departamental de Aguas -PDA- los recursos comprometidos a través de Acuerdo Municipal en el cuatrienio. | H33: 1 | I33: 1 | J33: =IF(OR($H33="",$I33=""),"",IFERROR($I33/$H33,0)) -> 1 | K33: 5.5332459e+08 | L33: 5.5332459e+08 | M33: =IF(OR($K33="",$L33=""),"",IFERROR($L33/$K33,0)) -> 1 | N33: Transferencia del 60% del toral de los recursos de APSB al PDA vigencia 2025 | O33: SGP - APSB | P33: Cumplida | Q33: Certificación | T33: =IF($A33="","",TODAY()) -> 46059
A34: 2024 | B34: Secretaría de Planeación y Obras Públicas | C34: META-091 | D34: =IF($C34="","",INDEX(PLAN_DESARROLLO!$B:$B,MATCH($C34,PLAN_DESARROLLO!$A:$A,0))) -> 2024257770017 | E34: =IF($C34="","",INDEX(PLAN_DESARROLLO!$C:$C,MATCH($C34,PLAN_DESARROLLO!$A:$A,0))) -> POR EL SUPATÁ SOÑADO AVANZAMOS JUNTOS EN LA LÍNEA ESTRATÉGICA SOCIAL | F34: =IF($C34="","",INDEX(PLAN_DESARROLLO!$D:$D,MATCH($C34,PLAN_DESARROLLO!$A:$A,0))) -> A.P.S.B | G34: =IF($C34="","",INDEX(PLAN_DESARROLLO!$E:$E,MATCH($C34,PLAN_DESARROLLO!$A:$A,0))) -> Realizar anulmente doce (12) analisis de calidad del agua de acuerdo a la resolucion 2115 de 2007 | H34: 12 | I34: 7 | J34: =IF(OR($H34="",$I34=""),"",IFERROR($I34/$H34,0)) -> 0.58333333 | K34: 8554315 | L34: 8554315 | M34: =IF(OR($K34="",$L34=""),"",IFERROR($L34/$K34,0)) -> 1 | N34: Contrato de Prestacion de Servicios No. CPS-093-2024 Cuyo objeto fue realizar las muestras y análisis de calidad de agua suministrada por el acueducto urbano, garantizando así un suministro de agua apta para consumo humano | O34: Recursos Propios | P34: Cumplida | Q34: Informe | T34: =IF($A34="","",TODAY()) -> 46059
A35: 2025 | B35: Secretaría de Planeación y Obras Públicas | C35: META-091 | D35: =IF($C35="","",INDEX(PLAN_DESARROLLO!$B:$B,MATCH($C35,PLAN_DESARROLLO!$A:$A,0))) -> 2024257770017 | E35: =IF($C35="","",INDEX(PLAN_DESARROLLO!$C:$C,MATCH($C35,PLAN_DESARROLLO!$A:$A,0))) -> POR EL SUPATÁ SOÑADO AVANZAMOS JUNTOS EN LA LÍNEA ESTRATÉGICA SOCIAL | F35: =IF($C35="","",INDEX(PLAN_DESARROLLO!$D:$D,MATCH($C35,PLAN_DESARROLLO!$A:$A,0))) -> A.P.S.B | G35: =IF($C35="","",INDEX(PLAN_DESARROLLO!$E:$E,MATCH($C35,PLAN_DESARROLLO!$A:$A,0))) -> Realizar anulmente doce (12) analisis de calidad del agua de acuerdo a la resolucion 2115 de 2007 | H35: 12 | I35: 12 | J35: =IF(OR($H35="",$I35=""),"",IFERROR($I35/$H35,0)) -> 1 | K35: 8827420 | L35: 8827420 | M35: =IF(OR($K35="",$L35=""),"",IFERROR($L35/$K35,0)) -> 1 | N35: Contrato de Prestacion de Servicios No. CPS-079-2025 Prestacion de servicios para la toma y analisis de agua potable en el sistema de acueducto urbano del municipio de supata cundinamarca. | O35: Recursos Propios | P35: Cumplida | Q35: Informe | T35: =IF($A35="","",TODAY()) -> 46059
A36: 2024 | B36: Secretaría de Planeación y Obras Públicas | C36: META-092 | D36: =IF($C36="","",INDEX(PLAN_DESARROLLO!$B:$B,MATCH($C36,PLAN_DESARROLLO!$A:$A,0))) -> 2024257770017 | E36: =IF($C36="","",INDEX(PLAN_DESARROLLO!$C:$C,MATCH($C36,PLAN_DESARROLLO!$A:$A,0))) -> POR EL SUPATÁ SOÑADO AVANZAMOS JUNTOS EN LA LÍNEA ESTRATÉGICA SOCIAL | F36: =IF($C36="","",INDEX(PLAN_DESARROLLO!$D:$D,MATCH($C36,PLAN_DESARROLLO!$A:$A,0))) -> A.P.S.B | G36: =IF($C36="","",INDEX(PLAN_DESARROLLO!$E:$E,MATCH($C36,PLAN_DESARROLLO!$A:$A,0))) -> elaborar el programa de Uso Eficiente y Ahorro del Agua (PUEAA) en el municipio durante el cuatrienio | H36: 1 | I36: 1 | J36: =IF(OR($H36="",$I36=""),"",IFERROR($I36/$H36,0)) -> 1 | K36: 34900000 | L36: 34900000 | M36: =IF(OR($K36="",$L36=""),"",IFERROR($L36/$K36,0)) -> 1 | N36: Contrato de Prestacion de Servicios No. CPS-135-2024 con el cual se elaboró el Plan de Uso Eficiente y Ahorro del Agua – PUEAA para el acueducto urbano | O36: SGP - APSB | P36: Cumplida | Q36: Informe | T36: =IF($A36="","",TODAY()) -> 46059
A37: 2025 | B37: Secretaría de Planeación y Obras Públicas | C37: META-092 | D37: =IF($C37="","",INDEX(PLAN_DESARROLLO!$B:$B,MATCH($C37,PLAN_DESARROLLO!$A:$A,0))) -> 2024257770017 | E37: =IF($C37="","",INDEX(PLAN_DESARROLLO!$C:$C,MATCH($C37,PLAN_DESARROLLO!$A:$A,0))) -> POR EL SUPATÁ SOÑADO AVANZAMOS JUNTOS EN LA LÍNEA ESTRATÉGICA SOCIAL | F37: =IF($C37="","",INDEX(PLAN_DESARROLLO!$D:$D,MATCH($C37,PLAN_DESARROLLO!$A:$A,0))) -> A.P.S.B | G37: =IF($C37="","",INDEX(PLAN_DESARROLLO!$E:$E,MATCH($C37,PLAN_DESARROLLO!$A:$A,0))) -> elaborar el programa de Uso Eficiente y Ahorro del Agua (PUEAA) en el municipio durante el cuatrienio | H37: 0 | I37: 0 | J37: =IF(OR($H37="",$I37=""),"",IFERROR($I37/$H37,0)) -> 0 | K37: 0 | L37: 0 | M37: =IF(OR($K37="",$L37=""),"",IFERROR($L37/$K37,0)) -> 0 | T37: =IF($A37="","",TODAY()) -> 46059
A38: 2024 | B38: Secretaría de Planeación y Obras Públicas | C38: META-093 | D38: =IF($C38="","",INDEX(PLAN_DESARROLLO!$B:$B,MATCH($C38,PLAN_DESARROLLO!$A:$A,0))) -> 2024257770017 | E38: =IF($C38="","",INDEX(PLAN_DESARROLLO!$C:$C,MATCH($C38,PLAN_DESARROLLO!$A:$A,0))) -> POR EL SUPATÁ SOÑADO AVANZAMOS JUNTOS EN LA LÍNEA ESTRATÉGICA SOCIAL | F38: =IF($C38="","",INDEX(PLAN_DESARROLLO!$D:$D,MATCH($C38,PLAN_DESARROLLO!$A:$A,0))) -> A.P.S.B | G38: =IF($C38="","",INDEX(PLAN_DESARROLLO!$E:$E,MATCH($C38,PLAN_DESARROLLO!$A:$A,0))) -> Acompañamiento para la legalizacion de acueductos veredales con requisitos minimos | H38: 1 | I38: 2 | J38: =IF(OR($H38="",$I38=""),"",IFERROR($I38/$H38,0)) -> 2 | K38: 0 | L38: 0 | M38: =IF(OR($K38="",$L38=""),"",IFERROR($L38/$K38,0)) -> 0 | N38: Se realizo acompañamiento al Acueducto la Cabrera y Acueducto Regional de las veredas Santa Rosa, Providencia, Cristales y Mesitas, permitiendoles así participar en la convocatoria de Agua a la Vereda de EPC saliendo beneficiados de este programa | P38: Cumplida | Q38: Informe | T38: =IF($A38="","",TODAY()) -> 46059
A39: 2025 | B39: Secretaría de Planeación y Obras Públicas | C39: META-093 | D39: =IF($C39="","",INDEX(PLAN_DESARROLLO!$B:$B,MATCH($C39,PLAN_DESARROLLO!$A:$A,0))) -> 2024257770017 | E39: =IF($C39="","",INDEX(PLAN_DESARROLLO!$C:$C,MATCH($C39,PLAN_DESARROLLO!$A:$A,0))) -> POR EL SUPATÁ SOÑADO AVANZAMOS JUNTOS EN LA LÍNEA ESTRATÉGICA SOCIAL | F39: =IF($C39="","",INDEX(PLAN_DESARROLLO!$D:$D,MATCH($C39,PLAN_DESARROLLO!$A:$A,0))) -> A.P.S.B | G39: =IF($C39="","",INDEX(PLAN_DESARROLLO!$E:$E,MATCH($C39,PLAN_DESARROLLO!$A:$A,0))) -> Acompañamiento para la legalizacion de acueductos veredales con requisitos minimos | H39: 1 | I39: 1 | J39: =IF(OR($H39="",$I39=""),"",IFERROR($I39/$H39,0)) -> 1 | K39: 0 | L39: 0 | M39: =IF(OR($K39="",$L39=""),"",IFERROR($L39/$K39,0)) -> 0 | N39: Se realizo acompañamiento al Acueducto de Monte Dulce permitiendole participar en la convocatoria de Agua a la Vereda de EPC saliendo beneficiado de este programa | P39: Cumplida | Q39: Informe | T39: =IF($A39="","",TODAY()) -> 46059
A40: 2024 | B40: Secretaría de Planeación y Obras Públicas | C40: META-094 | D40: =IF($C40="","",INDEX(PLAN_DESARROLLO!$B:$B,MATCH($C40,PLAN_DESARROLLO!$A:$A,0))) -> 2024257770017 | E40: =IF($C40="","",INDEX(PLAN_DESARROLLO!$C:$C,MATCH($C40,PLAN_DESARROLLO!$A:$A,0))) -> POR EL SUPATÁ SOÑADO AVANZAMOS JUNTOS EN LA LÍNEA ESTRATÉGICA SOCIAL | F40: =IF($C40="","",INDEX(PLAN_DESARROLLO!$D:$D,MATCH($C40,PLAN_DESARROLLO!$A:$A,0))) -> A.P.S.B | G40: =IF($C40="","",INDEX(PLAN_DESARROLLO!$E:$E,MATCH($C40,PLAN_DESARROLLO!$A:$A,0))) -> implementacion de un programa de micromedicion en el area urbana | H40: 1 | I40: 1 | J40: =IF(OR($H40="",$I40=""),"",IFERROR($I40/$H40,0)) -> 1 | K40: 19665552 | L40: 19665552 | M40: =IF(OR($K40="",$L40=""),"",IFERROR($L40/$K40,0)) -> 1 | N40: Acta de aceptacion de oferta proceso de selección MC 032-2024 Contrato de Compra No. COM-010-2024 Compra de equipos de micromedicion de agua potable en el marco de la implementacion de un programa de micromedicion en el acuedcuto urbano del Municipio de Supatá Cundinamarca. | O40: SGP - APSB | P40: Cumplida | Q40: Informe | T40: =IF($A40="","",TODAY()) -> 46059
A41: 2025 | B41: Secretaría de Planeación y Obras Públicas | C41: META-094 | D41: =IF($C41="","",INDEX(PLAN_DESARROLLO!$B:$B,MATCH($C41,PLAN_DESARROLLO!$A:$A,0))) -> 2024257770017 | E41: =IF($C41="","",INDEX(PLAN_DESARROLLO!$C:$C,MATCH($C41,PLAN_DESARROLLO!$A:$A,0))) -> POR EL SUPATÁ SOÑADO AVANZAMOS JUNTOS EN LA LÍNEA ESTRATÉGICA SOCIAL | F41: =IF($C41="","",INDEX(PLAN_DESARROLLO!$D:$D,MATCH($C41,PLAN_DESARROLLO!$A:$A,0))) -> A.P.S.B | G41: =IF($C41="","",INDEX(PLAN_DESARROLLO!$E:$E,MATCH($C41,PLAN_DESARROLLO!$A:$A,0))) -> implementacion de un programa de micromedicion en el area urbana | H41: 1 | I41: 0 | J41: =IF(OR($H41="",$I41=""),"",IFERROR($I41/$H41,0)) -> 0 | K41: 0 | L41: 0 | M41: =IF(OR($K41="",$L41=""),"",IFERROR($L41/$K41,0)) -> 0 | T41: =IF($A41="","",TODAY()) -> 46059
A42: 2024 | B42: Secretaría de Planeación y Obras Públicas | C42: META-095 | D42: =IF($C42="","",INDEX(PLAN_DESARROLLO!$B:$B,MATCH($C42,PLAN_DESARROLLO!$A:$A,0))) -> 2024257770017 | E42: =IF($C42="","",INDEX(PLAN_DESARROLLO!$C:$C,MATCH($C42,PLAN_DESARROLLO!$A:$A,0))) -> POR EL SUPATÁ SOÑADO AVANZAMOS JUNTOS EN LA LÍNEA ESTRATÉGICA SOCIAL | F42: =IF($C42="","",INDEX(PLAN_DESARROLLO!$D:$D,MATCH($C42,PLAN_DESARROLLO!$A:$A,0))) -> A.P.S.B | G42: =IF($C42="","",INDEX(PLAN_DESARROLLO!$E:$E,MATCH($C42,PLAN_DESARROLLO!$A:$A,0))) -> Realizar anulmente el fortalecimiento para el reporte de la informacion de las entidades de control | H42: 1 | I42: 1 | J42: =IF(OR($H42="",$I42=""),"",IFERROR($I42/$H42,0)) -> 1 | K42: 14700000 | L42: 14700000 | M42: =IF(OR($K42="",$L42=""),"",IFERROR($L42/$K42,0)) -> 1 | N42: Contrato de Prestacion de Servicios No. CPS-091-2024 Cuyo objeto fue Servicios profesionales deasesoria para el fortalecimiento en el reporte de la informacion orientada al cumplimiento de la regulacion y normatividad vigente en materia de agua potable y saneamiento basico de la oficina de servicios publicos del Municipio de Supatá | O42: Recursos Propios | P42: Cumplida | Q42: Informe | T42: =IF($A42="","",TODAY()) -> 46059
A43: 2025 | B43: Secretaría de Planeación y Obras Públicas | C43: META-095 | D43: =IF($C43="","",INDEX(PLAN_DESARROLLO!$B:$B,MATCH($C43,PLAN_DESARROLLO!$A:$A,0))) -> 2024257770017 | E43: =IF($C43="","",INDEX(PLAN_DESARROLLO!$C:$C,MATCH($C43,PLAN_DESARROLLO!$A:$A,0))) -> POR EL SUPATÁ SOÑADO AVANZAMOS JUNTOS EN LA LÍNEA ESTRATÉGICA SOCIAL | F43: =IF($C43="","",INDEX(PLAN_DESARROLLO!$D:$D,MATCH($C43,PLAN_DESARROLLO!$A:$A,0))) -> A.P.S.B | G43: =IF($C43="","",INDEX(PLAN_DESARROLLO!$E:$E,MATCH($C43,PLAN_DESARROLLO!$A:$A,0))) -> Realizar anulmente el fortalecimiento para el reporte de la informacion de las entidades de control | H43: 1 | I43: 1 | J43: =IF(OR($H43="",$I43=""),"",IFERROR($I43/$H43,0)) -> 1 | K43: 25080000 | L43: 25080000 | M43: =IF(OR($K43="",$L43=""),"",IFERROR($L43/$K43,0)) -> 1 | N43: Contrato de Prestacion de Servicios No. CPS-045-2025. Prestar los servicios profesionales de asesoria para el fortalecimiento en el reporte de información orientado al cumplimiento de la regulación y normatividad vigente en materia de agua potable y saneamiento basico de la oficina de servicios publicos del Municipio de Supatá Cundinamarca, conforme a los lineamientos establecidos en el plan de desarrollo municipal | O43: Recursos Propios | P43: Cumplida | Q43: Informe | T43: =IF($A43="","",TODAY()) -> 46059
A44: 2024 | B44: Secretaría de Planeación y Obras Públicas | C44: META-096 | D44: =IF($C44="","",INDEX(PLAN_DESARROLLO!$B:$B,MATCH($C44,PLAN_DESARROLLO!$A:$A,0))) -> 2024257770017 | E44: =IF($C44="","",INDEX(PLAN_DESARROLLO!$C:$C,MATCH($C44,PLAN_DESARROLLO!$A:$A,0))) -> POR EL SUPATÁ SOÑADO AVANZAMOS JUNTOS EN LA LÍNEA ESTRATÉGICA SOCIAL | F44: =IF($C44="","",INDEX(PLAN_DESARROLLO!$D:$D,MATCH($C44,PLAN_DESARROLLO!$A:$A,0))) -> A.P.S.B | G44: =IF($C44="","",INDEX(PLAN_DESARROLLO!$E:$E,MATCH($C44,PLAN_DESARROLLO!$A:$A,0))) -> Actualizar el Plan de Saneamiento y Manejo de Vertimientos (PSMV) | H44: 1 | I44: 0 | J44: =IF(OR($H44="",$I44=""),"",IFERROR($I44/$H44,0)) -> 0 | K44: 0 | L44: 0 | M44: =IF(OR($K44="",$L44=""),"",IFERROR($L44/$K44,0)) -> 0 | T44: =IF($A44="","",TODAY()) -> 46059
A45: 2025 | B45: Secretaría de Planeación y Obras Públicas | C45: META-096 | D45: =IF($C45="","",INDEX(PLAN_DESARROLLO!$B:$B,MATCH($C45,PLAN_DESARROLLO!$A:$A,0))) -> 2024257770017 | E45: =IF($C45="","",INDEX(PLAN_DESARROLLO!$C:$C,MATCH($C45,PLAN_DESARROLLO!$A:$A,0))) -> POR EL SUPATÁ SOÑADO AVANZAMOS JUNTOS EN LA LÍNEA ESTRATÉGICA SOCIAL | F45: =IF($C45="","",INDEX(PLAN_DESARROLLO!$D:$D,MATCH($C45,PLAN_DESARROLLO!$A:$A,0))) -> A.P.S.B | G45: =IF($C45="","",INDEX(PLAN_DESARROLLO!$E:$E,MATCH($C45,PLAN_DESARROLLO!$A:$A,0))) -> Actualizar el Plan de Saneamiento y Manejo de Vertimientos (PSMV) | H45: 1 | I45: 2 | J45: =IF(OR($H45="",$I45=""),"",IFERROR($I45/$H45,0)) -> 2 | K45: 0 | L45: 0 | M45: =IF(OR($K45="",$L45=""),"",IFERROR($L45/$K45,0)) -> 0 | N45: Actualización del PSMV Urbano y del Centro Poblado la Magola, a taves de Empresas Publicas de Cundinamarca - EPC | O45: SGP - APSB PDA | P45: Cumplida | Q45: Informe | T45: =IF($A45="","",TODAY()) -> 46059
A46: 2024 | B46: Secretaría de Planeación y Obras Públicas | C46: META-097 | D46: =IF($C46="","",INDEX(PLAN_DESARROLLO!$B:$B,MATCH($C46,PLAN_DESARROLLO!$A:$A,0))) -> 2024257770017 | E46: =IF($C46="","",INDEX(PLAN_DESARROLLO!$C:$C,MATCH($C46,PLAN_DESARROLLO!$A:$A,0))) -> POR EL SUPATÁ SOÑADO AVANZAMOS JUNTOS EN LA LÍNEA ESTRATÉGICA SOCIAL | F46: =IF($C46="","",INDEX(PLAN_DESARROLLO!$D:$D,MATCH($C46,PLAN_DESARROLLO!$A:$A,0))) -> A.P.S.B | G46: =IF($C46="","",INDEX(PLAN_DESARROLLO!$E:$E,MATCH($C46,PLAN_DESARROLLO!$A:$A,0))) -> gestionar la ejecución el Plan Maestro de Acueducto y Alcantarillado | H46: 0 | I46: 0 | J46: =IF(OR($H46="",$I46=""),"",IFERROR($I46/$H46,0)) -> 0 | K46: 0 | L46: 0 | M46: =IF(OR($K46="",$L46=""),"",IFERROR($L46/$K46,0)) -> 0 | T46: =IF($A46="","",TODAY()) -> 46059
A47: 2025 | B47: Secretaría de Planeación y Obras Públicas | C47: META-097 | D47: =IF($C47="","",INDEX(PLAN_DESARROLLO!$B:$B,MATCH($C47,PLAN_DESARROLLO!$A:$A,0))) -> 2024257770017 | E47: =IF($C47="","",INDEX(PLAN_DESARROLLO!$C:$C,MATCH($C47,PLAN_DESARROLLO!$A:$A,0))) -> POR EL SUPATÁ SOÑADO AVANZAMOS JUNTOS EN LA LÍNEA ESTRATÉGICA SOCIAL | F47: =IF($C47="","",INDEX(PLAN_DESARROLLO!$D:$D,MATCH($C47,PLAN_DESARROLLO!$A:$A,0))) -> A.P.S.B | G47: =IF($C47="","",INDEX(PLAN_DESARROLLO!$E:$E,MATCH($C47,PLAN_DESARROLLO!$A:$A,0))) -> gestionar la ejecución el Plan Maestro de Acueducto y Alcantarillado | H47: 10 | I47: 0 | J47: =IF(OR($H47="",$I47=""),"",IFERROR($I47/$H47,0)) -> 0 | K47: 0 | L47: 0 | M47: =IF(OR($K47="",$L47=""),"",IFERROR($L47/$K47,0)) -> 0 | N47: Se presento el proyecto de construccion del Plan Maestro de Acueducto y Alcantarillado Etapa Planta de Tratamiento de Agua Potable PTAP del area urbana a ventanilla Nacional para la consecucion de Recursos. | O47: Ministerio de Vivienda Ciudad y Territorio | T47: =IF($A47="","",TODAY()) -> 46059
A48: 2024 | B48: Secretaría de Planeación y Obras Públicas | C48: META-098 | D48: =IF($C48="","",INDEX(PLAN_DESARROLLO!$B:$B,MATCH($C48,PLAN_DESARROLLO!$A:$A,0))) -> 2024257770017 | E48: =IF($C48="","",INDEX(PLAN_DESARROLLO!$C:$C,MATCH($C48,PLAN_DESARROLLO!$A:$A,0))) -> POR EL SUPATÁ SOÑADO AVANZAMOS JUNTOS EN LA LÍNEA ESTRATÉGICA SOCIAL | F48: =IF($C48="","",INDEX(PLAN_DESARROLLO!$D:$D,MATCH($C48,PLAN_DESARROLLO!$A:$A,0))) -> A.P.S.B | G48: =IF($C48="","",INDEX(PLAN_DESARROLLO!$E:$E,MATCH($C48,PLAN_DESARROLLO!$A:$A,0))) -> Otorgar anualmente subsidios a los usuarios del servicio de alcantarillado de los estratos 1, 2 y 3 del área urbana,en el cuatrienio | H48: 1 | I48: 1 | J48: =IF(OR($H48="",$I48=""),"",IFERROR($I48/$H48,0)) -> 1 | K48: 11083682 | L48: 11083682 | M48: =IF(OR($K48="",$L48=""),"",IFERROR($L48/$K48,0)) -> 1 | N48: Pago de subsidios del servicio de Alcantarillado | O48: SGP - APSB | P48: Cumplida | Q48: Certificación | T48: =IF($A48="","",TODAY()) -> 46059
A49: 2025 | B49: Secretaría de Planeación y Obras Públicas | C49: META-098 | D49: =IF($C49="","",INDEX(PLAN_DESARROLLO!$B:$B,MATCH($C49,PLAN_DESARROLLO!$A:$A,0))) -> 2024257770017 | E49: =IF($C49="","",INDEX(PLAN_DESARROLLO!$C:$C,MATCH($C49,PLAN_DESARROLLO!$A:$A,0))) -> POR EL SUPATÁ SOÑADO AVANZAMOS JUNTOS EN LA LÍNEA ESTRATÉGICA SOCIAL | F49: =IF($C49="","",INDEX(PLAN_DESARROLLO!$D:$D,MATCH($C49,PLAN_DESARROLLO!$A:$A,0))) -> A.P.S.B | G49: =IF($C49="","",INDEX(PLAN_DESARROLLO!$E:$E,MATCH($C49,PLAN_DESARROLLO!$A:$A,0))) -> Otorgar anualmente subsidios a los usuarios del servicio de alcantarillado de los estratos 1, 2 y 3 del área urbana,en el cuatrienio | H49: 1 | I49: 1 | J49: =IF(OR($H49="",$I49=""),"",IFERROR($I49/$H49,0)) -> 1 | K49: 12346758 | L49: 12346758 | M49: =IF(OR($K49="",$L49=""),"",IFERROR($L49/$K49,0)) -> 1 | N49: Pago de subsidios del servicio de Alcantarillado | O49: SGP - APSB | P49: Cumplida | Q49: Certificación | T49: =IF($A49="","",TODAY()) -> 46059
A50: 2024 | B50: Secretaría de Planeación y Obras Públicas | C50: META-099 | D50: =IF($C50="","",INDEX(PLAN_DESARROLLO!$B:$B,MATCH($C50,PLAN_DESARROLLO!$A:$A,0))) -> 2024257770017 | E50: =IF($C50="","",INDEX(PLAN_DESARROLLO!$C:$C,MATCH($C50,PLAN_DESARROLLO!$A:$A,0))) -> POR EL SUPATÁ SOÑADO AVANZAMOS JUNTOS EN LA LÍNEA ESTRATÉGICA SOCIAL | F50: =IF($C50="","",INDEX(PLAN_DESARROLLO!$D:$D,MATCH($C50,PLAN_DESARROLLO!$A:$A,0))) -> A.P.S.B | G50: =IF($C50="","",INDEX(PLAN_DESARROLLO!$E:$E,MATCH($C50,PLAN_DESARROLLO!$A:$A,0))) -> Mejoramiento de la planta de tratamiento de aguas residuales -PTAR- del Municipio | H50: 0 | I50: 0 | J50: =IF(OR($H50="",$I50=""),"",IFERROR($I50/$H50,0)) -> 0 | K50: 0 | L50: 0 | M50: =IF(OR($K50="",$L50=""),"",IFERROR($L50/$K50,0)) -> 0 | T50: =IF($A50="","",TODAY()) -> 46059
A51: 2025 | B51: Secretaría de Planeación y Obras Públicas | C51: META-099 | D51: =IF($C51="","",INDEX(PLAN_DESARROLLO!$B:$B,MATCH($C51,PLAN_DESARROLLO!$A:$A,0))) -> 2024257770017 | E51: =IF($C51="","",INDEX(PLAN_DESARROLLO!$C:$C,MATCH($C51,PLAN_DESARROLLO!$A:$A,0))) -> POR EL SUPATÁ SOÑADO AVANZAMOS JUNTOS EN LA LÍNEA ESTRATÉGICA SOCIAL | F51: =IF($C51="","",INDEX(PLAN_DESARROLLO!$D:$D,MATCH($C51,PLAN_DESARROLLO!$A:$A,0))) -> A.P.S.B | G51: =IF($C51="","",INDEX(PLAN_DESARROLLO!$E:$E,MATCH($C51,PLAN_DESARROLLO!$A:$A,0))) -> Mejoramiento de la planta de tratamiento de aguas residuales -PTAR- del Municipio | H51: 0 | I51: 0 | J51: =IF(OR($H51="",$I51=""),"",IFERROR($I51/$H51,0)) -> 0 | K51: 0 | L51: 0 | M51: =IF(OR($K51="",$L51=""),"",IFERROR($L51/$K51,0)) -> 0 | T51: =IF($A51="","",TODAY()) -> 46059
A52: 2024 | B52: Secretaría de Planeación y Obras Públicas | C52: META-100 | D52: =IF($C52="","",INDEX(PLAN_DESARROLLO!$B:$B,MATCH($C52,PLAN_DESARROLLO!$A:$A,0))) -> 2024257770017 | E52: =IF($C52="","",INDEX(PLAN_DESARROLLO!$C:$C,MATCH($C52,PLAN_DESARROLLO!$A:$A,0))) -> POR EL SUPATÁ SOÑADO AVANZAMOS JUNTOS EN LA LÍNEA ESTRATÉGICA SOCIAL | F52: =IF($C52="","",INDEX(PLAN_DESARROLLO!$D:$D,MATCH($C52,PLAN_DESARROLLO!$A:$A,0))) -> A.P.S.B | G52: =IF($C52="","",INDEX(PLAN_DESARROLLO!$E:$E,MATCH($C52,PLAN_DESARROLLO!$A:$A,0))) -> Realizar mejoramiento al alcantarillado sanitario y pluvial | H52: 0 | I52: 0 | J52: =IF(OR($H52="",$I52=""),"",IFERROR($I52/$H52,0)) -> 0 | K52: 0 | L52: 0 | M52: =IF(OR($K52="",$L52=""),"",IFERROR($L52/$K52,0)) -> 0 | T52: =IF($A52="","",TODAY()) -> 46059
A53: 2025 | B53: Secretaría de Planeación y Obras Públicas | C53: META-100 | D53: =IF($C53="","",INDEX(PLAN_DESARROLLO!$B:$B,MATCH($C53,PLAN_DESARROLLO!$A:$A,0))) -> 2024257770017 | E53: =IF($C53="","",INDEX(PLAN_DESARROLLO!$C:$C,MATCH($C53,PLAN_DESARROLLO!$A:$A,0))) -> POR EL SUPATÁ SOÑADO AVANZAMOS JUNTOS EN LA LÍNEA ESTRATÉGICA SOCIAL | F53: =IF($C53="","",INDEX(PLAN_DESARROLLO!$D:$D,MATCH($C53,PLAN_DESARROLLO!$A:$A,0))) -> A.P.S.B | G53: =IF($C53="","",INDEX(PLAN_DESARROLLO!$E:$E,MATCH($C53,PLAN_DESARROLLO!$A:$A,0))) -> Realizar mejoramiento al alcantarillado sanitario y pluvial | H53: 1 | I53: 2 | J53: =IF(OR($H53="",$I53=""),"",IFERROR($I53/$H53,0)) -> 2 | K53: =36438601.87+39778078.8 -> 76216681 | L53: =36438601.87+39778078.8 -> 76216681 | M53: =IF(OR($K53="",$L53=""),"",IFERROR($L53/$K53,0)) -> 1 | N53: COP-001-2025 Optimizacion y mejoramiento alcantarillado Carrea 7 entre Calles 2 y perimetro urbano, COP-002-2025 Optimizacion y mejoramiento alcantarillado de la Carrera 5 entre Calles 4 y 5 | O53: SGP - APSB | P53: Cumplida | Q53: Informe | T53: =IF($A53="","",TODAY()) -> 46059
A54: 2024 | B54: Secretaría de Planeación y Obras Públicas | C54: META-101 | D54: =IF($C54="","",INDEX(PLAN_DESARROLLO!$B:$B,MATCH($C54,PLAN_DESARROLLO!$A:$A,0))) -> 2024257770017 | E54: =IF($C54="","",INDEX(PLAN_DESARROLLO!$C:$C,MATCH($C54,PLAN_DESARROLLO!$A:$A,0))) -> POR EL SUPATÁ SOÑADO AVANZAMOS JUNTOS EN LA LÍNEA ESTRATÉGICA SOCIAL | F54: =IF($C54="","",INDEX(PLAN_DESARROLLO!$D:$D,MATCH($C54,PLAN_DESARROLLO!$A:$A,0))) -> A.P.S.B | G54: =IF($C54="","",INDEX(PLAN_DESARROLLO!$E:$E,MATCH($C54,PLAN_DESARROLLO!$A:$A,0))) -> Implementar el Plan de gestión integral de residuos sólidos (PGIRS) del municipio en el marco de la Resolución No. 754 de 2014 , la Política Nacional para la Gestión Integral de Residuos Sólidos – CONPES 3874 de 2016, y la Resolución 2184 de 2019, en el cuatrenio | H54: 1 | I54: 1 | J54: =IF(OR($H54="",$I54=""),"",IFERROR($I54/$H54,0)) -> 1 | K54: 55984572 | L54: 55984572 | M54: =IF(OR($K54="",$L54=""),"",IFERROR($L54/$K54,0)) -> 1 | N54: Convenio de Asociacion No 002-2024 Entre el Municipio de Supatá y la Fundacion Ecoarcoiris para la implementacion del Plan de Gestion integral de Residuos Solidos - PGIRS | O54: SGP - APSB | P54: Cumplida | Q54: Informe | T54: =IF($A54="","",TODAY()) -> 46059
A55: 2025 | B55: Secretaría de Planeación y Obras Públicas | C55: META-101 | D55: =IF($C55="","",INDEX(PLAN_DESARROLLO!$B:$B,MATCH($C55,PLAN_DESARROLLO!$A:$A,0))) -> 2024257770017 | E55: =IF($C55="","",INDEX(PLAN_DESARROLLO!$C:$C,MATCH($C55,PLAN_DESARROLLO!$A:$A,0))) -> POR EL SUPATÁ SOÑADO AVANZAMOS JUNTOS EN LA LÍNEA ESTRATÉGICA SOCIAL | F55: =IF($C55="","",INDEX(PLAN_DESARROLLO!$D:$D,MATCH($C55,PLAN_DESARROLLO!$A:$A,0))) -> A.P.S.B | G55: =IF($C55="","",INDEX(PLAN_DESARROLLO!$E:$E,MATCH($C55,PLAN_DESARROLLO!$A:$A,0))) -> Implementar el Plan de gestión integral de residuos sólidos (PGIRS) del municipio en el marco de la Resolución No. 754 de 2014 , la Política Nacional para la Gestión Integral de Residuos Sólidos – CONPES 3874 de 2016, y la Resolución 2184 de 2019, en el cuatrenio | H55: 1 | I55: 1 | J55: =IF(OR($H55="",$I55=""),"",IFERROR($I55/$H55,0)) -> 1 | M55: =IF(OR($K55="",$L55=""),"",IFERROR($L55/$K55,0)) | N55: Apoyo de la Secretaria de Bienestar Verde del Departamento a la Asociacion de Recicladores con Dotacion y la entrega de una Prensa para material reciclable. | O55: Gobernación | P55: Cumplida | Q55: Informe | T55: =IF($A55="","",TODAY()) -> 46059
A56: 2024 | B56: Secretaría de Planeación y Obras Públicas | C56: META-102 | D56: =IF($C56="","",INDEX(PLAN_DESARROLLO!$B:$B,MATCH($C56,PLAN_DESARROLLO!$A:$A,0))) -> 2024257770017 | E56: =IF($C56="","",INDEX(PLAN_DESARROLLO!$C:$C,MATCH($C56,PLAN_DESARROLLO!$A:$A,0))) -> POR EL SUPATÁ SOÑADO AVANZAMOS JUNTOS EN LA LÍNEA ESTRATÉGICA SOCIAL | F56: =IF($C56="","",INDEX(PLAN_DESARROLLO!$D:$D,MATCH($C56,PLAN_DESARROLLO!$A:$A,0))) -> A.P.S.B | G56: =IF($C56="","",INDEX(PLAN_DESARROLLO!$E:$E,MATCH($C56,PLAN_DESARROLLO!$A:$A,0))) -> Otorgar anualmente subsidios a los usuarios del servicio de aseo de los estratos 1, 2 y 3 del área urbana,en el cuatrienio | H56: 1 | I56: 1 | J56: =IF(OR($H56="",$I56=""),"",IFERROR($I56/$H56,0)) -> 1 | K56: 11510599 | L56: 11510599 | M56: =IF(OR($K56="",$L56=""),"",IFERROR($L56/$K56,0)) -> 1 | N56: Pago de subsidios del servicio de Aseo | O56: SGP - APSB | P56: Cumplida | Q56: Certificación | T56: =IF($A56="","",TODAY()) -> 46059
A57: 2025 | B57: Secretaría de Planeación y Obras Públicas | C57: META-102 | D57: =IF($C57="","",INDEX(PLAN_DESARROLLO!$B:$B,MATCH($C57,PLAN_DESARROLLO!$A:$A,0))) -> 2024257770017 | E57: =IF($C57="","",INDEX(PLAN_DESARROLLO!$C:$C,MATCH($C57,PLAN_DESARROLLO!$A:$A,0))) -> POR EL SUPATÁ SOÑADO AVANZAMOS JUNTOS EN LA LÍNEA ESTRATÉGICA SOCIAL | F57: =IF($C57="","",INDEX(PLAN_DESARROLLO!$D:$D,MATCH($C57,PLAN_DESARROLLO!$A:$A,0))) -> A.P.S.B | G57: =IF($C57="","",INDEX(PLAN_DESARROLLO!$E:$E,MATCH($C57,PLAN_DESARROLLO!$A:$A,0))) -> Otorgar anualmente subsidios a los usuarios del servicio de aseo de los estratos 1, 2 y 3 del área urbana,en el cuatrienio | H57: 1 | I57: 1 | J57: =IF(OR($H57="",$I57=""),"",IFERROR($I57/$H57,0)) -> 1 | K57: 12045673 | L57: 12045673 | M57: =IF(OR($K57="",$L57=""),"",IFERROR($L57/$K57,0)) -> 1 | N57: Pago de subsidios del servicio de Aseo | O57: SGP - APSB | P57: Cumplida | Q57: Certificación | T57: =IF($A57="","",TODAY()) -> 46059
A58: 2024 | B58: Secretaría de Planeación y Obras Públicas | C58: META-120 | D58: =IF($C58="","",INDEX(PLAN_DESARROLLO!$B:$B,MATCH($C58,PLAN_DESARROLLO!$A:$A,0))) -> 2024257770021 | E58: =IF($C58="","",INDEX(PLAN_DESARROLLO!$C:$C,MATCH($C58,PLAN_DESARROLLO!$A:$A,0))) -> POR EL SUPATÁ SOÑADO AVANZAMOS JUNTOS EN LA LÍNEA ESTRATÉGICA ECONÓMICA | F58: =IF($C58="","",INDEX(PLAN_DESARROLLO!$D:$D,MATCH($C58,PLAN_DESARROLLO!$A:$A,0))) -> TRANSPORTE | G58: =IF($C58="","",INDEX(PLAN_DESARROLLO!$E:$E,MATCH($C58,PLAN_DESARROLLO!$A:$A,0))) -> Adquirir maquinaria amarilla | H58: 1 | I58: 0 | J58: =IF(OR($H58="",$I58=""),"",IFERROR($I58/$H58,0)) -> 0 | K58: 0 | L58: 0 | M58: =IF(OR($K58="",$L58=""),"",IFERROR($L58/$K58,0)) -> 0 | N58: se vienen adelantando las gestiones para adquirir esta maquinaria amarilla | O58: Gobernación | P58: No iniciada | Q58: Otro | T58: =IF($A58="","",TODAY()) -> 46059
A59: 2025 | B59: Secretaría de Planeación y Obras Públicas | C59: META-120 | D59: =IF($C59="","",INDEX(PLAN_DESARROLLO!$B:$B,MATCH($C59,PLAN_DESARROLLO!$A:$A,0))) -> 2024257770021 | E59: =IF($C59="","",INDEX(PLAN_DESARROLLO!$C:$C,MATCH($C59,PLAN_DESARROLLO!$A:$A,0))) -> POR EL SUPATÁ SOÑADO AVANZAMOS JUNTOS EN LA LÍNEA ESTRATÉGICA ECONÓMICA | F59: =IF($C59="","",INDEX(PLAN_DESARROLLO!$D:$D,MATCH($C59,PLAN_DESARROLLO!$A:$A,0))) -> TRANSPORTE | G59: =IF($C59="","",INDEX(PLAN_DESARROLLO!$E:$E,MATCH($C59,PLAN_DESARROLLO!$A:$A,0))) -> Adquirir maquinaria amarilla | H59: 1 | I59: 1 | J59: =IF(OR($H59="",$I59=""),"",IFERROR($I59/$H59,0)) -> 1 | K59: 900000000 | L59: 900000000 | M59: =IF(OR($K59="",$L59=""),"",IFERROR($L59/$K59,0)) -> 1 | N59: convenio interadministrativo entre el municipio de supata y la gobernacion de cundinamarca | O59: Mixta | P59: Cumplida | Q59: Informe | T59: =IF($A59="","",TODAY()) -> 46059
A60: 2024 | B60: Secretaría de Planeación y Obras Públicas | C60: META-121 | D60: =IF($C60="","",INDEX(PLAN_DESARROLLO!$B:$B,MATCH($C60,PLAN_DESARROLLO!$A:$A,0))) -> 2024257770021 | E60: =IF($C60="","",INDEX(PLAN_DESARROLLO!$C:$C,MATCH($C60,PLAN_DESARROLLO!$A:$A,0))) -> POR EL SUPATÁ SOÑADO AVANZAMOS JUNTOS EN LA LÍNEA ESTRATÉGICA ECONÓMICA | F60: =IF($C60="","",INDEX(PLAN_DESARROLLO!$D:$D,MATCH($C60,PLAN_DESARROLLO!$A:$A,0))) -> TRANSPORTE | G60: =IF($C60="","",INDEX(PLAN_DESARROLLO!$E:$E,MATCH($C60,PLAN_DESARROLLO!$A:$A,0))) -> Realizar 3 mantenimientos a la maquinaria amarilla propiedad del municipio | H60: 3 | I60: 3 | J60: =IF(OR($H60="",$I60=""),"",IFERROR($I60/$H60,0)) -> 1 | K60: 100000000 | L60: 100000000 | M60: =IF(OR($K60="",$L60=""),"",IFERROR($L60/$K60,0)) -> 1 | N60: mentenimiento rutinarios a la maquinaria del municipio | O60: SGP | P60: Cumplida | Q60: Informe | T60: =IF($A60="","",TODAY()) -> 46059
A61: 2025 | B61: Secretaría de Planeación y Obras Públicas | C61: META-121 | D61: =IF($C61="","",INDEX(PLAN_DESARROLLO!$B:$B,MATCH($C61,PLAN_DESARROLLO!$A:$A,0))) -> 2024257770021 | E61: =IF($C61="","",INDEX(PLAN_DESARROLLO!$C:$C,MATCH($C61,PLAN_DESARROLLO!$A:$A,0))) -> POR EL SUPATÁ SOÑADO AVANZAMOS JUNTOS EN LA LÍNEA ESTRATÉGICA ECONÓMICA | F61: =IF($C61="","",INDEX(PLAN_DESARROLLO!$D:$D,MATCH($C61,PLAN_DESARROLLO!$A:$A,0))) -> TRANSPORTE | G61: =IF($C61="","",INDEX(PLAN_DESARROLLO!$E:$E,MATCH($C61,PLAN_DESARROLLO!$A:$A,0))) -> Realizar 3 mantenimientos a la maquinaria amarilla propiedad del municipio | H61: 3 | I61: 3 | J61: =IF(OR($H61="",$I61=""),"",IFERROR($I61/$H61,0)) -> 1 | K61: 100000000 | L61: 100000000 | M61: =IF(OR($K61="",$L61=""),"",IFERROR($L61/$K61,0)) -> 1 | N61: mentenimiento rutinarios a la maquinaria del municipio | O61: SGP | P61: Cumplida | Q61: Informe | T61: =IF($A61="","",TODAY()) -> 46059
A62: 2024 | B62: Secretaría de Planeación y Obras Públicas | C62: META-122 | D62: =IF($C62="","",INDEX(PLAN_DESARROLLO!$B:$B,MATCH($C62,PLAN_DESARROLLO!$A:$A,0))) -> 2024257770021 | E62: =IF($C62="","",INDEX(PLAN_DESARROLLO!$C:$C,MATCH($C62,PLAN_DESARROLLO!$A:$A,0))) -> POR EL SUPATÁ SOÑADO AVANZAMOS JUNTOS EN LA LÍNEA ESTRATÉGICA ECONÓMICA | F62: =IF($C62="","",INDEX(PLAN_DESARROLLO!$D:$D,MATCH($C62,PLAN_DESARROLLO!$A:$A,0))) -> TRANSPORTE | G62: =IF($C62="","",INDEX(PLAN_DESARROLLO!$E:$E,MATCH($C62,PLAN_DESARROLLO!$A:$A,0))) -> Realizar la apertura de 2 km de vías terciarias dentro del municipio | H62: 2 | I62: 2 | J62: =IF(OR($H62="",$I62=""),"",IFERROR($I62/$H62,0)) -> 1 | K62: 0 | L62: 0 | M62: =IF(OR($K62="",$L62=""),"",IFERROR($L62/$K62,0)) -> 0 | N62: se realizan ajustes y mejoramientos a pasos abandonados | O62: SGP | P62: Cumplida | Q62: Informe | T62: =IF($A62="","",TODAY()) -> 46059
A63: 2025 | B63: Secretaría de Planeación y Obras Públicas | C63: META-122 | D63: =IF($C63="","",INDEX(PLAN_DESARROLLO!$B:$B,MATCH($C63,PLAN_DESARROLLO!$A:$A,0))) -> 2024257770021 | E63: =IF($C63="","",INDEX(PLAN_DESARROLLO!$C:$C,MATCH($C63,PLAN_DESARROLLO!$A:$A,0))) -> POR EL SUPATÁ SOÑADO AVANZAMOS JUNTOS EN LA LÍNEA ESTRATÉGICA ECONÓMICA | F63: =IF($C63="","",INDEX(PLAN_DESARROLLO!$D:$D,MATCH($C63,PLAN_DESARROLLO!$A:$A,0))) -> TRANSPORTE | G63: =IF($C63="","",INDEX(PLAN_DESARROLLO!$E:$E,MATCH($C63,PLAN_DESARROLLO!$A:$A,0))) -> Realizar la apertura de 2 km de vías terciarias dentro del municipio | H63: 2 | I63: 2 | J63: =IF(OR($H63="",$I63=""),"",IFERROR($I63/$H63,0)) -> 1 | K63: 0 | L63: 0 | M63: =IF(OR($K63="",$L63=""),"",IFERROR($L63/$K63,0)) -> 0 | N63: se realizan ajustes y mejoramientos a pasos abandonados | O63: SGP | P63: Cumplida | Q63: Informe | T63: =IF($A63="","",TODAY()) -> 46059
A64: 2024 | B64: Secretaría de Planeación y Obras Públicas | C64: META-123 | D64: =IF($C64="","",INDEX(PLAN_DESARROLLO!$B:$B,MATCH($C64,PLAN_DESARROLLO!$A:$A,0))) -> 2024257770021 | E64: =IF($C64="","",INDEX(PLAN_DESARROLLO!$C:$C,MATCH($C64,PLAN_DESARROLLO!$A:$A,0))) -> POR EL SUPATÁ SOÑADO AVANZAMOS JUNTOS EN LA LÍNEA ESTRATÉGICA ECONÓMICA | F64: =IF($C64="","",INDEX(PLAN_DESARROLLO!$D:$D,MATCH($C64,PLAN_DESARROLLO!$A:$A,0))) -> TRANSPORTE | G64: =IF($C64="","",INDEX(PLAN_DESARROLLO!$E:$E,MATCH($C64,PLAN_DESARROLLO!$A:$A,0))) -> Realizar el mantenimiento, rehabilitación y adecuación de 100 ML de vías en la zona urbana del municipio, en el periodo de gobierno | H64: 100 | I64: 0 | J64: =IF(OR($H64="",$I64=""),"",IFERROR($I64/$H64,0)) -> 0 | K64: 0 | L64: 0 | M64: =IF(OR($K64="",$L64=""),"",IFERROR($L64/$K64,0)) -> 0 | N64: se vienen adelantando las gestiones para cumplir con el objetivo | O64: Gobernación | P64: No iniciada | Q64: Informe | T64: =IF($A64="","",TODAY()) -> 46059
A65: 2025 | B65: Secretaría de Planeación y Obras Públicas | C65: META-123 | D65: =IF($C65="","",INDEX(PLAN_DESARROLLO!$B:$B,MATCH($C65,PLAN_DESARROLLO!$A:$A,0))) -> 2024257770021 | E65: =IF($C65="","",INDEX(PLAN_DESARROLLO!$C:$C,MATCH($C65,PLAN_DESARROLLO!$A:$A,0))) -> POR EL SUPATÁ SOÑADO AVANZAMOS JUNTOS EN LA LÍNEA ESTRATÉGICA ECONÓMICA | F65: =IF($C65="","",INDEX(PLAN_DESARROLLO!$D:$D,MATCH($C65,PLAN_DESARROLLO!$A:$A,0))) -> TRANSPORTE | G65: =IF($C65="","",INDEX(PLAN_DESARROLLO!$E:$E,MATCH($C65,PLAN_DESARROLLO!$A:$A,0))) -> Realizar el mantenimiento, rehabilitación y adecuación de 100 ML de vías en la zona urbana del municipio, en el periodo de gobierno | H65: 100 | I65: 600 | J65: =IF(OR($H65="",$I65=""),"",IFERROR($I65/$H65,0)) -> 6 | K65: =1970000000+600000000 -> 2570000000 | L65: =1970000000+600000000 -> 2570000000 | M65: =IF(OR($K65="",$L65=""),"",IFERROR($L65/$K65,0)) -> 1 | N65: convenio interadministrativo entre la gobernacion de cundinamarca y el municipio de supata | O65: Gobernación | P65: Cumplida | Q65: Informe | T65: =IF($A65="","",TODAY()) -> 46059
A66: 2024 | B66: Secretaría de Planeación y Obras Públicas | C66: META-124 | D66: =IF($C66="","",INDEX(PLAN_DESARROLLO!$B:$B,MATCH($C66,PLAN_DESARROLLO!$A:$A,0))) -> 2024257770021 | E66: =IF($C66="","",INDEX(PLAN_DESARROLLO!$C:$C,MATCH($C66,PLAN_DESARROLLO!$A:$A,0))) -> POR EL SUPATÁ SOÑADO AVANZAMOS JUNTOS EN LA LÍNEA ESTRATÉGICA ECONÓMICA | F66: =IF($C66="","",INDEX(PLAN_DESARROLLO!$D:$D,MATCH($C66,PLAN_DESARROLLO!$A:$A,0))) -> TRANSPORTE | G66: =IF($C66="","",INDEX(PLAN_DESARROLLO!$E:$E,MATCH($C66,PLAN_DESARROLLO!$A:$A,0))) -> Mejoramiento y mantenimiento 2 puentes vehiculares, en la zona rural o urbana del municipio | H66: 2 | I66: 0 | J66: =IF(OR($H66="",$I66=""),"",IFERROR($I66/$H66,0)) -> 0 | K66: 0 | L66: 0 | M66: =IF(OR($K66="",$L66=""),"",IFERROR($L66/$K66,0)) -> 0 | N66: se vienen adelantando gestiones para la adecuacion de los puentes | O66: Mixta | P66: No iniciada | Q66: Informe | T66: =IF($A66="","",TODAY()) -> 46059
A67: 2025 | B67: Secretaría de Planeación y Obras Públicas | C67: META-124 | D67: =IF($C67="","",INDEX(PLAN_DESARROLLO!$B:$B,MATCH($C67,PLAN_DESARROLLO!$A:$A,0))) -> 2024257770021 | E67: =IF($C67="","",INDEX(PLAN_DESARROLLO!$C:$C,MATCH($C67,PLAN_DESARROLLO!$A:$A,0))) -> POR EL SUPATÁ SOÑADO AVANZAMOS JUNTOS EN LA LÍNEA ESTRATÉGICA ECONÓMICA | F67: =IF($C67="","",INDEX(PLAN_DESARROLLO!$D:$D,MATCH($C67,PLAN_DESARROLLO!$A:$A,0))) -> TRANSPORTE | G67: =IF($C67="","",INDEX(PLAN_DESARROLLO!$E:$E,MATCH($C67,PLAN_DESARROLLO!$A:$A,0))) -> Mejoramiento y mantenimiento 2 puentes vehiculares, en la zona rural o urbana del municipio | H67: 2 | I67: 0 | J67: =IF(OR($H67="",$I67=""),"",IFERROR($I67/$H67,0)) -> 0 | K67: 0 | L67: 0 | M67: =IF(OR($K67="",$L67=""),"",IFERROR($L67/$K67,0)) -> 0 | N67: se vienen adelantando gestiones para la adecuacion de los puentes | O67: Mixta | P67: No iniciada | Q67: Informe | T67: =IF($A67="","",TODAY()) -> 46059
A68: 2024 | B68: Secretaría de Planeación y Obras Públicas | C68: META-125 | D68: =IF($C68="","",INDEX(PLAN_DESARROLLO!$B:$B,MATCH($C68,PLAN_DESARROLLO!$A:$A,0))) -> 2024257770021 | E68: =IF($C68="","",INDEX(PLAN_DESARROLLO!$C:$C,MATCH($C68,PLAN_DESARROLLO!$A:$A,0))) -> POR EL SUPATÁ SOÑADO AVANZAMOS JUNTOS EN LA LÍNEA ESTRATÉGICA ECONÓMICA | F68: =IF($C68="","",INDEX(PLAN_DESARROLLO!$D:$D,MATCH($C68,PLAN_DESARROLLO!$A:$A,0))) -> TRANSPORTE | G68: =IF($C68="","",INDEX(PLAN_DESARROLLO!$E:$E,MATCH($C68,PLAN_DESARROLLO!$A:$A,0))) -> Hacer mantenimiento y/o adecuación a 4 caminos reales durante el cuatrienio. | H68: 4 | I68: 4 | J68: =IF(OR($H68="",$I68=""),"",IFERROR($I68/$H68,0)) -> 1 | K68: 0 | L68: 0 | M68: =IF(OR($K68="",$L68=""),"",IFERROR($L68/$K68,0)) -> 0 | N68: se realizan mantenimientos, pero tambien la contratacion del personal para el cuidado y preservacion de estos espacios | O68: Recursos Propios | P68: Cumplida | Q68: Informe | T68: =IF($A68="","",TODAY()) -> 46059
A69: 2025 | B69: Secretaría de Planeación y Obras Públicas | C69: META-125 | D69: =IF($C69="","",INDEX(PLAN_DESARROLLO!$B:$B,MATCH($C69,PLAN_DESARROLLO!$A:$A,0))) -> 2024257770021 | E69: =IF($C69="","",INDEX(PLAN_DESARROLLO!$C:$C,MATCH($C69,PLAN_DESARROLLO!$A:$A,0))) -> POR EL SUPATÁ SOÑADO AVANZAMOS JUNTOS EN LA LÍNEA ESTRATÉGICA ECONÓMICA | F69: =IF($C69="","",INDEX(PLAN_DESARROLLO!$D:$D,MATCH($C69,PLAN_DESARROLLO!$A:$A,0))) -> TRANSPORTE | G69: =IF($C69="","",INDEX(PLAN_DESARROLLO!$E:$E,MATCH($C69,PLAN_DESARROLLO!$A:$A,0))) -> Hacer mantenimiento y/o adecuación a 4 caminos reales durante el cuatrienio. | H69: 4 | I69: 4 | J69: =IF(OR($H69="",$I69=""),"",IFERROR($I69/$H69,0)) -> 1 | K69: 0 | L69: 0 | M69: =IF(OR($K69="",$L69=""),"",IFERROR($L69/$K69,0)) -> 0 | N69: se realizan mantenimientos, pero tambien la contratacion del personal para el cuidado y preservacion de estos espacios | O69: Recursos Propios | P69: Cumplida | Q69: Informe | T69: =IF($A69="","",TODAY()) -> 46059
A70: 2024 | B70: Secretaría de Planeación y Obras Públicas | C70: META-126 | D70: =IF($C70="","",INDEX(PLAN_DESARROLLO!$B:$B,MATCH($C70,PLAN_DESARROLLO!$A:$A,0))) -> 2024257770021 | E70: =IF($C70="","",INDEX(PLAN_DESARROLLO!$C:$C,MATCH($C70,PLAN_DESARROLLO!$A:$A,0))) -> POR EL SUPATÁ SOÑADO AVANZAMOS JUNTOS EN LA LÍNEA ESTRATÉGICA ECONÓMICA | F70: =IF($C70="","",INDEX(PLAN_DESARROLLO!$D:$D,MATCH($C70,PLAN_DESARROLLO!$A:$A,0))) -> TRANSPORTE | G70: =IF($C70="","",INDEX(PLAN_DESARROLLO!$E:$E,MATCH($C70,PLAN_DESARROLLO!$A:$A,0))) -> Realizar 300 metros lineales de señalizacion de vías terciarias y urbanas del municipio. | H70: 300 | I70: 0 | J70: =IF(OR($H70="",$I70=""),"",IFERROR($I70/$H70,0)) -> 0 | K70: 0 | L70: 0 | M70: =IF(OR($K70="",$L70=""),"",IFERROR($L70/$K70,0)) -> 0 | N70: se vienen adelantando gestiones para el cumplimiento de la meta | O70: Recursos Propios | P70: No iniciada | Q70: Informe | T70: =IF($A70="","",TODAY()) -> 46059
A71: 2025 | B71: Secretaría de Planeación y Obras Públicas | C71: META-126 | D71: =IF($C71="","",INDEX(PLAN_DESARROLLO!$B:$B,MATCH($C71,PLAN_DESARROLLO!$A:$A,0))) -> 2024257770021 | E71: =IF($C71="","",INDEX(PLAN_DESARROLLO!$C:$C,MATCH($C71,PLAN_DESARROLLO!$A:$A,0))) -> POR EL SUPATÁ SOÑADO AVANZAMOS JUNTOS EN LA LÍNEA ESTRATÉGICA ECONÓMICA | F71: =IF($C71="","",INDEX(PLAN_DESARROLLO!$D:$D,MATCH($C71,PLAN_DESARROLLO!$A:$A,0))) -> TRANSPORTE | G71: =IF($C71="","",INDEX(PLAN_DESARROLLO!$E:$E,MATCH($C71,PLAN_DESARROLLO!$A:$A,0))) -> Realizar 300 metros lineales de señalizacion de vías terciarias y urbanas del municipio. | H71: 300 | I71: 0 | J71: =IF(OR($H71="",$I71=""),"",IFERROR($I71/$H71,0)) -> 0 | K71: 0 | L71: 0 | M71: =IF(OR($K71="",$L71=""),"",IFERROR($L71/$K71,0)) -> 0 | N71: se vienen adelantando gestiones para el cumplimiento de la meta | O71: Recursos Propios | P71: No iniciada | Q71: Informe | T71: =IF($A71="","",TODAY()) -> 46059
A72: 2024 | B72: Secretaría de Planeación y Obras Públicas | C72: META-127 | D72: =IF($C72="","",INDEX(PLAN_DESARROLLO!$B:$B,MATCH($C72,PLAN_DESARROLLO!$A:$A,0))) -> 2024257770021 | E72: =IF($C72="","",INDEX(PLAN_DESARROLLO!$C:$C,MATCH($C71,PLAN_DESARROLLO!$A:$A,0))) -> POR EL SUPATÁ SOÑADO AVANZAMOS JUNTOS EN LA LÍNEA ESTRATÉGICA ECONÓMICA | F72: =IF($C72="","",INDEX(PLAN_DESARROLLO!$D:$D,MATCH($C71,PLAN_DESARROLLO!$A:$A,0))) -> TRANSPORTE | G72: =IF($C72="","",INDEX(PLAN_DESARROLLO!$E:$E,MATCH($C72,PLAN_DESARROLLO!$A:$A,0))) -> Realizar 4 capacitaciones sobre seguridad vial a los actores viales del municipio | H72: 0 | I72: 0 | J72: =IF(OR($H72="",$I72=""),"",IFERROR($I72/$H72,0)) -> 0 | K72: 0 | L72: 0 | M72: =IF(OR($K72="",$L72=""),"",IFERROR($L72/$K72,0)) -> 0 | N72: en proceso de verificacion | O72: Mixta | P72: No iniciada | Q72: Informe | T72: =IF($A72="","",TODAY()) -> 46059
A73: 2025 | B73: Secretaría de Planeación y Obras Públicas | C73: META-127 | D73: =IF($C73="","",INDEX(PLAN_DESARROLLO!$B:$B,MATCH($C73,PLAN_DESARROLLO!$A:$A,0))) -> 2024257770021 | E73: =IF($C73="","",INDEX(PLAN_DESARROLLO!$C:$C,MATCH($C71,PLAN_DESARROLLO!$A:$A,0))) -> POR EL SUPATÁ SOÑADO AVANZAMOS JUNTOS EN LA LÍNEA ESTRATÉGICA ECONÓMICA | F73: =IF($C73="","",INDEX(PLAN_DESARROLLO!$D:$D,MATCH($C71,PLAN_DESARROLLO!$A:$A,0))) -> TRANSPORTE | G73: =IF($C73="","",INDEX(PLAN_DESARROLLO!$E:$E,MATCH($C73,PLAN_DESARROLLO!$A:$A,0))) -> Realizar 4 capacitaciones sobre seguridad vial a los actores viales del municipio | H73: 0 | I73: 0 | J73: =IF(OR($H73="",$I73=""),"",IFERROR($I73/$H73,0)) -> 0 | K73: 0 | L73: 0 | M73: =IF(OR($K73="",$L73=""),"",IFERROR($L73/$K73,0)) -> 0 | N73: en proceso de verificacion | O73: Mixta | P73: No iniciada | Q73: Informe | T73: =IF($A73="","",TODAY()) -> 46059
A74: 2024 | B74: Secretaría de Planeación y Obras Públicas | C74: META-144 | D74: =IF($C74="","",INDEX(PLAN_DESARROLLO!$B:$B,MATCH($C74,PLAN_DESARROLLO!$A:$A,0))) -> 2024257770029 | E74: =IF($C74="","",INDEX(PLAN_DESARROLLO!$C:$C,MATCH($C74,PLAN_DESARROLLO!$A:$A,0))) -> POR EL SUPATÁ SOÑADO AVANZAMOS JUNTOS EN LA LÍNEA ESTRATÉGICA ECONÓMICA | F74: =IF($C74="","",INDEX(PLAN_DESARROLLO!$D:$D,MATCH($C74,PLAN_DESARROLLO!$A:$A,0))) -> AGROPECUARIO | G74: =IF($C74="","",INDEX(PLAN_DESARROLLO!$E:$E,MATCH($C74,PLAN_DESARROLLO!$A:$A,0))) -> gestionar los estudios y diseños de un centro de acopio para productos agropecuarios. | H74: 1 | I74: 0 | J74: =IF(OR($H74="",$I74=""),"",IFERROR($I74/$H74,0)) -> 0 | K74: 0 | L74: 0 | M74: =IF(OR($K74="",$L74=""),"",IFERROR($L74/$K74,0)) -> 0 | N74: se vienen adelantando gestiones para el cumplimiento de la meta | O74: Recursos Propios | P74: No iniciada | Q74: Informe | T74: =IF($A74="","",TODAY()) -> 46059
A75: 2025 | B75: Secretaría de Planeación y Obras Públicas | C75: META-144 | D75: =IF($C75="","",INDEX(PLAN_DESARROLLO!$B:$B,MATCH($C75,PLAN_DESARROLLO!$A:$A,0))) -> 2024257770029 | E75: =IF($C75="","",INDEX(PLAN_DESARROLLO!$C:$C,MATCH($C75,PLAN_DESARROLLO!$A:$A,0))) -> POR EL SUPATÁ SOÑADO AVANZAMOS JUNTOS EN LA LÍNEA ESTRATÉGICA ECONÓMICA | F75: =IF($C75="","",INDEX(PLAN_DESARROLLO!$D:$D,MATCH($C75,PLAN_DESARROLLO!$A:$A,0))) -> AGROPECUARIO | G75: =IF($C75="","",INDEX(PLAN_DESARROLLO!$E:$E,MATCH($C75,PLAN_DESARROLLO!$A:$A,0))) -> gestionar los estudios y diseños de un centro de acopio para productos agropecuarios. | H75: 1 | I75: 0 | J75: =IF(OR($H75="",$I75=""),"",IFERROR($I75/$H75,0)) -> 0 | K75: 0 | L75: 0 | M75: =IF(OR($K75="",$L75=""),"",IFERROR($L75/$K75,0)) -> 0 | N75: se vienen adelantando gestiones para el cumplimiento de la meta | O75: Recursos Propios | P75: No iniciada | Q75: Informe | T75: =IF($A75="","",TODAY()) -> 46059
A76: 2024 | B76: Secretaría de Planeación y Obras Públicas | C76: META-148 | D76: =IF($C76="","",INDEX(PLAN_DESARROLLO!$B:$B,MATCH($C76,PLAN_DESARROLLO!$A:$A,0))) -> 2024257770030 | E76: =IF($C76="","",INDEX(PLAN_DESARROLLO!$C:$C,MATCH($C76,PLAN_DESARROLLO!$A:$A,0))) -> POR EL SUPATÁ SOÑADO AVANZAMOS JUNTOS EN LA LÍNEA ESTRATÉGICA INSTITUCIONAL | F76: =IF($C76="","",INDEX(PLAN_DESARROLLO!$D:$D,MATCH($C76,PLAN_DESARROLLO!$A:$A,0))) -> FORTALECIMIENTO INSTITUCIONAL | G76: =IF($C76="","",INDEX(PLAN_DESARROLLO!$E:$E,MATCH($C76,PLAN_DESARROLLO!$A:$A,0))) -> Realizar un mantenimiento anual de los bienes inmuebles de propiedad del municipio en el cuatrienio. | H76: 1 | I76: 1 | J76: =IF(OR($H76="",$I76=""),"",IFERROR($I76/$H76,0)) -> 1 | K76: 30000000 | L76: 30000000 | M76: =IF(OR($K76="",$L76=""),"",IFERROR($L76/$K76,0)) -> 1 | N76: al crear el banco de materiales, se puede contar con disponibilidad para adecuacion de los espacios institucionales | O76: Recursos Propios | P76: Cumplida | Q76: Informe | T76: =IF($A76="","",TODAY()) -> 46059
A77: 2025 | B77: Secretaría de Planeación y Obras Públicas | C77: META-148 | D77: =IF($C77="","",INDEX(PLAN_DESARROLLO!$B:$B,MATCH($C77,PLAN_DESARROLLO!$A:$A,0))) -> 2024257770030 | E77: =IF($C77="","",INDEX(PLAN_DESARROLLO!$C:$C,MATCH($C77,PLAN_DESARROLLO!$A:$A,0))) -> POR EL SUPATÁ SOÑADO AVANZAMOS JUNTOS EN LA LÍNEA ESTRATÉGICA INSTITUCIONAL | F77: =IF($C77="","",INDEX(PLAN_DESARROLLO!$D:$D,MATCH($C77,PLAN_DESARROLLO!$A:$A,0))) -> FORTALECIMIENTO INSTITUCIONAL | G77: =IF($C77="","",INDEX(PLAN_DESARROLLO!$E:$E,MATCH($C77,PLAN_DESARROLLO!$A:$A,0))) -> Realizar un mantenimiento anual de los bienes inmuebles de propiedad del municipio en el cuatrienio. | H77: 1 | I77: 1 | J77: =IF(OR($H77="",$I77=""),"",IFERROR($I77/$H77,0)) -> 1 | K77: 30000000 | L77: 30000000 | M77: =IF(OR($K77="",$L77=""),"",IFERROR($L77/$K77,0)) -> 1 | N77: arreglos locativos a sedes institucionales | O77: Recursos Propios | P77: Cumplida | Q77: Informe | T77: =IF($A77="","",TODAY()) -> 46059
A78: 2024 | B78: Secretaría de Planeación y Obras Públicas | C78: META-149 | D78: =IF($C78="","",INDEX(PLAN_DESARROLLO!$B:$B,MATCH($C78,PLAN_DESARROLLO!$A:$A,0))) -> 2024257770030 | E78: =IF($C78="","",INDEX(PLAN_DESARROLLO!$C:$C,MATCH($C78,PLAN_DESARROLLO!$A:$A,0))) -> POR EL SUPATÁ SOÑADO AVANZAMOS JUNTOS EN LA LÍNEA ESTRATÉGICA INSTITUCIONAL | F78: =IF($C78="","",INDEX(PLAN_DESARROLLO!$D:$D,MATCH($C78,PLAN_DESARROLLO!$A:$A,0))) -> FORTALECIMIENTO INSTITUCIONAL | G78: =IF($C78="","",INDEX(PLAN_DESARROLLO!$E:$E,MATCH($C78,PLAN_DESARROLLO!$A:$A,0))) -> Realizar construcción de la infraestructura de la Casa de Gobierno del municipio | H78: 1 | I78: 0 | J78: =IF(OR($H78="",$I78=""),"",IFERROR($I78/$H78,0)) -> 0 | K78: 0 | L78: 0 | M78: =IF(OR($K78="",$L78=""),"",IFERROR($L78/$K78,0)) -> 0 | N78: se estan adelantando los estudios y diseños | O78: Mixta | P78: En ejecución | Q78: Informe | T78: =IF($A78="","",TODAY()) -> 46059
A79: 2025 | B79: Secretaría de Planeación y Obras Públicas | C79: META-149 | D79: =IF($C79="","",INDEX(PLAN_DESARROLLO!$B:$B,MATCH($C79,PLAN_DESARROLLO!$A:$A,0))) -> 2024257770030 | E79: =IF($C79="","",INDEX(PLAN_DESARROLLO!$C:$C,MATCH($C79,PLAN_DESARROLLO!$A:$A,0))) -> POR EL SUPATÁ SOÑADO AVANZAMOS JUNTOS EN LA LÍNEA ESTRATÉGICA INSTITUCIONAL | F79: =IF($C79="","",INDEX(PLAN_DESARROLLO!$D:$D,MATCH($C79,PLAN_DESARROLLO!$A:$A,0))) -> FORTALECIMIENTO INSTITUCIONAL | G79: =IF($C79="","",INDEX(PLAN_DESARROLLO!$E:$E,MATCH($C79,PLAN_DESARROLLO!$A:$A,0))) -> Realizar construcción de la infraestructura de la Casa de Gobierno del municipio | H79: 1 | I79: 1 | J79: =IF(OR($H79="",$I79=""),"",IFERROR($I79/$H79,0)) -> 1 | K79: 3970000000 | L79: 3970000000 | M79: =IF(OR($K79="",$L79=""),"",IFERROR($L79/$K79,0)) -> 1 | N79: =N23 -> en proceso de adjudicacion luego de ser aprobados los estudios y diseños, en convenio entre la gobernacion de cundinamarca y los fondos por regalias | O79: Mixta | P79: En ejecución | Q79: Informe | T79: =IF($A79="","",TODAY()) -> 46059
A80: 2024 | B80: Secretaría de Planeación y Obras Públicas | C80: META-154 | D80: =IF($C80="","",INDEX(PLAN_DESARROLLO!$B:$B,MATCH($C80,PLAN_DESARROLLO!$A:$A,0))) -> 2024257770031 | E80: =IF($C80="","",INDEX(PLAN_DESARROLLO!$C:$C,MATCH($C80,PLAN_DESARROLLO!$A:$A,0))) -> POR EL SUPATÁ SOÑADO AVANZAMOS JUNTOS EN LA LÍNEA ESTRATÉGICA INSTITUCIONAL | F80: =IF($C80="","",INDEX(PLAN_DESARROLLO!$D:$D,MATCH($C80,PLAN_DESARROLLO!$A:$A,0))) -> FORTALECIMIENTO INSTITUCIONAL | G80: =IF($C80="","",INDEX(PLAN_DESARROLLO!$E:$E,MATCH($C80,PLAN_DESARROLLO!$A:$A,0))) -> Realizar (8) reuniones del CMGRD para el establecimiento de mecanismos alerta y reacción ante situaciones de riesgo. | H80: 8 | I80: 12 | J80: =IF(OR($H80="",$I80=""),"",IFERROR($I80/$H80,0)) -> 1.5 | K80: 0 | L80: 0 | M80: =IF(OR($K80="",$L80=""),"",IFERROR($L80/$K80,0)) -> 0 | N80: se realiza al menos 1 vez al mes un comité de gestion del riesgo | O80: Recursos Propios | P80: Cumplida | Q80: Informe | T80: =IF($A80="","",TODAY()) -> 46059
A81: 2025 | B81: Secretaría de Planeación y Obras Públicas | C81: META-154 | D81: =IF($C81="","",INDEX(PLAN_DESARROLLO!$B:$B,MATCH($C81,PLAN_DESARROLLO!$A:$A,0))) -> 2024257770031 | E81: =IF($C81="","",INDEX(PLAN_DESARROLLO!$C:$C,MATCH($C81,PLAN_DESARROLLO!$A:$A,0))) -> POR EL SUPATÁ SOÑADO AVANZAMOS JUNTOS EN LA LÍNEA ESTRATÉGICA INSTITUCIONAL | F81: =IF($C81="","",INDEX(PLAN_DESARROLLO!$D:$D,MATCH($C81,PLAN_DESARROLLO!$A:$A,0))) -> FORTALECIMIENTO INSTITUCIONAL | G81: =IF($C81="","",INDEX(PLAN_DESARROLLO!$E:$E,MATCH($C81,PLAN_DESARROLLO!$A:$A,0))) -> Realizar (8) reuniones del CMGRD para el establecimiento de mecanismos alerta y reacción ante situaciones de riesgo. | H81: 8 | I81: 15 | J81: =IF(OR($H81="",$I81=""),"",IFERROR($I81/$H81,0)) -> 1.875 | K81: 0 | L81: 0 | M81: =IF(OR($K81="",$L81=""),"",IFERROR($L81/$K81,0)) -> 0 | N81: se realiza al menos 1 vez al mes un comité de gestion del riesgo | O81: Recursos Propios | P81: Cumplida | Q81: Informe | T81: =IF($A81="","",TODAY()) -> 46059
A82: 2024 | B82: Secretaría de Planeación y Obras Públicas | C82: META-155 | D82: =IF($C82="","",INDEX(PLAN_DESARROLLO!$B:$B,MATCH($C82,PLAN_DESARROLLO!$A:$A,0))) -> 2024257770031 | E82: =IF($C82="","",INDEX(PLAN_DESARROLLO!$C:$C,MATCH($C82,PLAN_DESARROLLO!$A:$A,0))) -> POR EL SUPATÁ SOÑADO AVANZAMOS JUNTOS EN LA LÍNEA ESTRATÉGICA INSTITUCIONAL | F82: =IF($C82="","",INDEX(PLAN_DESARROLLO!$D:$D,MATCH($C82,PLAN_DESARROLLO!$A:$A,0))) -> FORTALECIMIENTO INSTITUCIONAL | G82: =IF($C82="","",INDEX(PLAN_DESARROLLO!$E:$E,MATCH($C82,PLAN_DESARROLLO!$A:$A,0))) -> Realizar un convenio con el cuerpo de bomberos | H82: 1 | I82: 1 | J82: =IF(OR($H82="",$I82=""),"",IFERROR($I82/$H82,0)) -> 1 | K82: 100000000 | L82: 100000000 | M82: =IF(OR($K82="",$L82=""),"",IFERROR($L82/$K82,0)) -> 1 | N82: se realiza convenio con el cuerpo de bomberos de san francisco | O82: Recursos Propios | P82: Cumplida | Q82: Informe | T82: =IF($A82="","",TODAY()) -> 46059
A83: 2025 | B83: Secretaría de Planeación y Obras Públicas | C83: META-155 | D83: =IF($C83="","",INDEX(PLAN_DESARROLLO!$B:$B,MATCH($C83,PLAN_DESARROLLO!$A:$A,0))) -> 2024257770031 | E83: =IF($C83="","",INDEX(PLAN_DESARROLLO!$C:$C,MATCH($C83,PLAN_DESARROLLO!$A:$A,0))) -> POR EL SUPATÁ SOÑADO AVANZAMOS JUNTOS EN LA LÍNEA ESTRATÉGICA INSTITUCIONAL | F83: =IF($C83="","",INDEX(PLAN_DESARROLLO!$D:$D,MATCH($C83,PLAN_DESARROLLO!$A:$A,0))) -> FORTALECIMIENTO INSTITUCIONAL | G83: =IF($C83="","",INDEX(PLAN_DESARROLLO!$E:$E,MATCH($C83,PLAN_DESARROLLO!$A:$A,0))) -> Realizar un convenio con el cuerpo de bomberos | H83: 1 | I83: 1 | J83: =IF(OR($H83="",$I83=""),"",IFERROR($I83/$H83,0)) -> 1 | K83: 100000000 | L83: 100000000 | M83: =IF(OR($K83="",$L83=""),"",IFERROR($L83/$K83,0)) -> 1 | N83: se realiza convenio con el cuerpo de bomberos de san francisco | O83: Recursos Propios | P83: Cumplida | Q83: Informe | T83: =IF($A83="","",TODAY()) -> 46059
A84: 2024 | B84: Secretaría de Planeación y Obras Públicas | C84: META-156 | D84: =IF($C84="","",INDEX(PLAN_DESARROLLO!$B:$B,MATCH($C84,PLAN_DESARROLLO!$A:$A,0))) -> 2024257770031 | E84: =IF($C84="","",INDEX(PLAN_DESARROLLO!$C:$C,MATCH($C84,PLAN_DESARROLLO!$A:$A,0))) -> POR EL SUPATÁ SOÑADO AVANZAMOS JUNTOS EN LA LÍNEA ESTRATÉGICA INSTITUCIONAL | F84: =IF($C84="","",INDEX(PLAN_DESARROLLO!$D:$D,MATCH($C84,PLAN_DESARROLLO!$A:$A,0))) -> FORTALECIMIENTO INSTITUCIONAL | G84: =IF($C84="","",INDEX(PLAN_DESARROLLO!$E:$E,MATCH($C84,PLAN_DESARROLLO!$A:$A,0))) -> Realizar obras de mitigación del Riesgo | H84: 1 | I84: 0 | J84: =IF(OR($H84="",$I84=""),"",IFERROR($I84/$H84,0)) -> 0 | K84: 0 | L84: 0 | M84: =IF(OR($K84="",$L84=""),"",IFERROR($L84/$K84,0)) -> 0 | N84: se estan adelantando los estudios y diseños | O84: Nación/Ministerios | P84: No iniciada | Q84: Informe | T84: =IF($A84="","",TODAY()) -> 46059
A85: 2025 | B85: Secretaría de Planeación y Obras Públicas | C85: META-156 | D85: =IF($C85="","",INDEX(PLAN_DESARROLLO!$B:$B,MATCH($C85,PLAN_DESARROLLO!$A:$A,0))) -> 2024257770031 | E85: =IF($C85="","",INDEX(PLAN_DESARROLLO!$C:$C,MATCH($C85,PLAN_DESARROLLO!$A:$A,0))) -> POR EL SUPATÁ SOÑADO AVANZAMOS JUNTOS EN LA LÍNEA ESTRATÉGICA INSTITUCIONAL | F85: =IF($C85="","",INDEX(PLAN_DESARROLLO!$D:$D,MATCH($C85,PLAN_DESARROLLO!$A:$A,0))) -> FORTALECIMIENTO INSTITUCIONAL | G85: =IF($C85="","",INDEX(PLAN_DESARROLLO!$E:$E,MATCH($C85,PLAN_DESARROLLO!$A:$A,0))) -> Realizar obras de mitigación del Riesgo | H85: 1 | I85: 0 | J85: =IF(OR($H85="",$I85=""),"",IFERROR($I85/$H85,0)) -> 0 | K85: 0 | L85: 0 | M85: =IF(OR($K85="",$L85=""),"",IFERROR($L85/$K85,0)) -> 0 | N85: se estan adelantando los estudios y diseños | O85: Nación/Ministerios | P85: No iniciada | Q85: Informe | T85: =IF($A85="","",TODAY()) -> 46059
A86: 2024 | B86: Secretaría de Planeación y Obras Públicas | C86: META-157 | D86: =IF($C86="","",INDEX(PLAN_DESARROLLO!$B:$B,MATCH($C86,PLAN_DESARROLLO!$A:$A,0))) -> 2024257770031 | E86: =IF($C86="","",INDEX(PLAN_DESARROLLO!$C:$C,MATCH($C86,PLAN_DESARROLLO!$A:$A,0))) -> POR EL SUPATÁ SOÑADO AVANZAMOS JUNTOS EN LA LÍNEA ESTRATÉGICA INSTITUCIONAL | F86: =IF($C86="","",INDEX(PLAN_DESARROLLO!$D:$D,MATCH($C86,PLAN_DESARROLLO!$A:$A,0))) -> FORTALECIMIENTO INSTITUCIONAL | G86: =IF($C86="","",INDEX(PLAN_DESARROLLO!$E:$E,MATCH($C86,PLAN_DESARROLLO!$A:$A,0))) -> Realizar anualmente (1) asistencia tecnica de apoyo a los grupos de socorro | H86: 1 | I86: 1 | J86: =IF(OR($H86="",$I86=""),"",IFERROR($I86/$H86,0)) -> 1 | K86: 0 | L86: 0 | M86: =IF(OR($K86="",$L86=""),"",IFERROR($L86/$K86,0)) -> 0 | N86: en conjunto con el convenio del cuerpo de bomberos de san francisoc se brindan capacitaciones | O86: Recursos Propios | P86: Cumplida | Q86: Informe | T86: =IF($A86="","",TODAY()) -> 46059
A87: 2025 | B87: Secretaría de Planeación y Obras Públicas | C87: META-157 | D87: =IF($C87="","",INDEX(PLAN_DESARROLLO!$B:$B,MATCH($C87,PLAN_DESARROLLO!$A:$A,0))) -> 2024257770031 | E87: =IF($C87="","",INDEX(PLAN_DESARROLLO!$C:$C,MATCH($C87,PLAN_DESARROLLO!$A:$A,0))) -> POR EL SUPATÁ SOÑADO AVANZAMOS JUNTOS EN LA LÍNEA ESTRATÉGICA INSTITUCIONAL | F87: =IF($C87="","",INDEX(PLAN_DESARROLLO!$D:$D,MATCH($C87,PLAN_DESARROLLO!$A:$A,0))) -> FORTALECIMIENTO INSTITUCIONAL | G87: =IF($C87="","",INDEX(PLAN_DESARROLLO!$E:$E,MATCH($C87,PLAN_DESARROLLO!$A:$A,0))) -> Realizar anualmente (1) asistencia tecnica de apoyo a los grupos de socorro | H87: 1 | I87: 1 | J87: =IF(OR($H87="",$I87=""),"",IFERROR($I87/$H87,0)) -> 1 | K87: 0 | L87: 0 | M87: 1 | N87: en conjunto con el convenio del cuerpo de bomberos de san francisoc se brindan capacitaciones | O87: Recursos Propios | P87: Cumplida | Q87: Informe | T87: =IF($A87="","",TODAY()) -> 46059
A88: 2024 | B88: Secretaría de Planeación y Obras Públicas | C88: META-158 | D88: =IF($C88="","",INDEX(PLAN_DESARROLLO!$B:$B,MATCH($C88,PLAN_DESARROLLO!$A:$A,0))) -> 2024257770031 | E88: =IF($C88="","",INDEX(PLAN_DESARROLLO!$C:$C,MATCH($C88,PLAN_DESARROLLO!$A:$A,0))) -> POR EL SUPATÁ SOÑADO AVANZAMOS JUNTOS EN LA LÍNEA ESTRATÉGICA INSTITUCIONAL | F88: =IF($C88="","",INDEX(PLAN_DESARROLLO!$D:$D,MATCH($C88,PLAN_DESARROLLO!$A:$A,0))) -> FORTALECIMIENTO INSTITUCIONAL | G88: =IF($C88="","",INDEX(PLAN_DESARROLLO!$E:$E,MATCH($C88,PLAN_DESARROLLO!$A:$A,0))) -> Actualizar el plan de gestión del riesgo de desastres y estrategia para la respuesta a emergencias | H88: 1 | I88: 0 | J88: =IF(OR($H88="",$I88=""),"",IFERROR($I88/$H88,0)) -> 0 | K88: 0 | L88: 0 | M88: =IF(OR($K88="",$L88=""),"",IFERROR($L88/$K88,0)) -> 0 | N88: esta en proceso de verificacion | O88: CAR | P88: No iniciada | Q88: Informe | T88: =IF($A88="","",TODAY()) -> 46059
A89: 2025 | B89: Secretaría de Planeación y Obras Públicas | C89: META-158 | D89: =IF($C89="","",INDEX(PLAN_DESARROLLO!$B:$B,MATCH($C89,PLAN_DESARROLLO!$A:$A,0))) -> 2024257770031 | E89: =IF($C89="","",INDEX(PLAN_DESARROLLO!$C:$C,MATCH($C89,PLAN_DESARROLLO!$A:$A,0))) -> POR EL SUPATÁ SOÑADO AVANZAMOS JUNTOS EN LA LÍNEA ESTRATÉGICA INSTITUCIONAL | F89: =IF($C89="","",INDEX(PLAN_DESARROLLO!$D:$D,MATCH($C89,PLAN_DESARROLLO!$A:$A,0))) -> FORTALECIMIENTO INSTITUCIONAL | G89: =IF($C89="","",INDEX(PLAN_DESARROLLO!$E:$E,MATCH($C89,PLAN_DESARROLLO!$A:$A,0))) -> Actualizar el plan de gestión del riesgo de desastres y estrategia para la respuesta a emergencias | H89: 1 | I89: 0 | J89: =IF(OR($H89="",$I89=""),"",IFERROR($I89/$H89,0)) -> 0 | K89: 0 | L89: 0 | M89: =IF(OR($K89="",$L89=""),"",IFERROR($L89/$K89,0)) -> 0 | N89: esta en proceso de verificacion | O89: CAR | P89: No iniciada | Q89: Informe | T89: =IF($A89="","",TODAY()) -> 46059
A90: 2024 | B90: Secretaría de Planeación y Obras Públicas | C90: META-159 | D90: =IF($C90="","",INDEX(PLAN_DESARROLLO!$B:$B,MATCH($C90,PLAN_DESARROLLO!$A:$A,0))) -> 2024257770031 | E90: =IF($C90="","",INDEX(PLAN_DESARROLLO!$C:$C,MATCH($C90,PLAN_DESARROLLO!$A:$A,0))) -> POR EL SUPATÁ SOÑADO AVANZAMOS JUNTOS EN LA LÍNEA ESTRATÉGICA INSTITUCIONAL | F90: =IF($C90="","",INDEX(PLAN_DESARROLLO!$D:$D,MATCH($C90,PLAN_DESARROLLO!$A:$A,0))) -> FORTALECIMIENTO INSTITUCIONAL | G90: =IF($C90="","",INDEX(PLAN_DESARROLLO!$E:$E,MATCH($C90,PLAN_DESARROLLO!$A:$A,0))) -> Capacitar a 20 lideres comunitarios en tema de atención y prevención de Gestión del Riesgo | H90: 20 | I90: 10 | J90: =IF(OR($H90="",$I90=""),"",IFERROR($I90/$H90,0)) -> 0.5 | K90: 0 | L90: 0 | M90: =IF(OR($K90="",$L90=""),"",IFERROR($L90/$K90,0)) -> 0 | N90: =N86 -> en conjunto con el convenio del cuerpo de bomberos de san francisoc se brindan capacitaciones | O90: Recursos Propios | P90: En ejecución | Q90: Informe | T90: =IF($A90="","",TODAY()) -> 46059
A91: 2025 | B91: Secretaría de Planeación y Obras Públicas | C91: META-159 | D91: =IF($C91="","",INDEX(PLAN_DESARROLLO!$B:$B,MATCH($C91,PLAN_DESARROLLO!$A:$A,0))) -> 2024257770031 | E91: =IF($C91="","",INDEX(PLAN_DESARROLLO!$C:$C,MATCH($C91,PLAN_DESARROLLO!$A:$A,0))) -> POR EL SUPATÁ SOÑADO AVANZAMOS JUNTOS EN LA LÍNEA ESTRATÉGICA INSTITUCIONAL | F91: =IF($C91="","",INDEX(PLAN_DESARROLLO!$D:$D,MATCH($C91,PLAN_DESARROLLO!$A:$A,0))) -> FORTALECIMIENTO INSTITUCIONAL | G91: =IF($C91="","",INDEX(PLAN_DESARROLLO!$E:$E,MATCH($C91,PLAN_DESARROLLO!$A:$A,0))) -> Capacitar a 20 lideres comunitarios en tema de atención y prevención de Gestión del Riesgo | H91: 20 | I91: 10 | J91: =IF(OR($H91="",$I91=""),"",IFERROR($I91/$H91,0)) -> 0.5 | K91: 0 | L91: 0 | M91: =IF(OR($K91="",$L91=""),"",IFERROR($L91/$K91,0)) -> 0 | N91: =N87 -> en conjunto con el convenio del cuerpo de bomberos de san francisoc se brindan capacitaciones | O91: Recursos Propios | P91: En ejecución | Q91: Informe | T91: =IF($A91="","",TODAY()) -> 46059
A92: 2024 | B92: Secretaría de Planeación y Obras Públicas | C92: META-160 | D92: =IF($C92="","",INDEX(PLAN_DESARROLLO!$B:$B,MATCH($C92,PLAN_DESARROLLO!$A:$A,0))) -> 2024257770031 | E92: =IF($C92="","",INDEX(PLAN_DESARROLLO!$C:$C,MATCH($C92,PLAN_DESARROLLO!$A:$A,0))) -> POR EL SUPATÁ SOÑADO AVANZAMOS JUNTOS EN LA LÍNEA ESTRATÉGICA INSTITUCIONAL | F92: =IF($C92="","",INDEX(PLAN_DESARROLLO!$D:$D,MATCH($C92,PLAN_DESARROLLO!$A:$A,0))) -> FORTALECIMIENTO INSTITUCIONAL | G92: =IF($C92="","",INDEX(PLAN_DESARROLLO!$E:$E,MATCH($C92,PLAN_DESARROLLO!$A:$A,0))) -> Realizar (4) simulacros de evacuación | H92: 4 | I92: 2 | J92: =IF(OR($H92="",$I92=""),"",IFERROR($I92/$H92,0)) -> 0.5 | K92: 0 | L92: 0 | M92: =IF(OR($K92="",$L92=""),"",IFERROR($L92/$K92,0)) -> 0 | N92: se realizan y verifican condiciones | O92: Recursos Propios | P92: En ejecución | Q92: Informe | T92: =IF($A92="","",TODAY()) -> 46059
A93: 2025 | B93: Secretaría de Planeación y Obras Públicas | C93: META-160 | D93: =IF($C93="","",INDEX(PLAN_DESARROLLO!$B:$B,MATCH($C93,PLAN_DESARROLLO!$A:$A,0))) -> 2024257770031 | E93: =IF($C93="","",INDEX(PLAN_DESARROLLO!$C:$C,MATCH($C93,PLAN_DESARROLLO!$A:$A,0))) -> POR EL SUPATÁ SOÑADO AVANZAMOS JUNTOS EN LA LÍNEA ESTRATÉGICA INSTITUCIONAL | F93: =IF($C93="","",INDEX(PLAN_DESARROLLO!$D:$D,MATCH($C93,PLAN_DESARROLLO!$A:$A,0))) -> FORTALECIMIENTO INSTITUCIONAL | G93: =IF($C93="","",INDEX(PLAN_DESARROLLO!$E:$E,MATCH($C93,PLAN_DESARROLLO!$A:$A,0))) -> Realizar (4) simulacros de evacuación | H93: 4 | I93: 2 | J93: =IF(OR($H93="",$I93=""),"",IFERROR($I93/$H93,0)) -> 0.5 | K93: 0 | L93: 0 | M93: =IF(OR($K93="",$L93=""),"",IFERROR($L93/$K93,0)) -> 0 | N93: se realizan y verifican condiciones | O93: Recursos Propios | P93: En ejecución | Q93: Informe | T93: =IF($A93="","",TODAY()) -> 46059
A94: 2024 | B94: Secretaría de Planeación y Obras Públicas | C94: META-161 | D94: =IF($C94="","",INDEX(PLAN_DESARROLLO!$B:$B,MATCH($C94,PLAN_DESARROLLO!$A:$A,0))) -> 2024257770031 | E94: =IF($C94="","",INDEX(PLAN_DESARROLLO!$C:$C,MATCH($C94,PLAN_DESARROLLO!$A:$A,0))) -> POR EL SUPATÁ SOÑADO AVANZAMOS JUNTOS EN LA LÍNEA ESTRATÉGICA INSTITUCIONAL | F94: =IF($C94="","",INDEX(PLAN_DESARROLLO!$D:$D,MATCH($C94,PLAN_DESARROLLO!$A:$A,0))) -> FORTALECIMIENTO INSTITUCIONAL | G94: =IF($C94="","",INDEX(PLAN_DESARROLLO!$E:$E,MATCH($C94,PLAN_DESARROLLO!$A:$A,0))) -> Implementar un programa anual para la ayuda humanitaria y la atención de la población afectada por desastres y emergencias sanitarias | H94: 1 | I94: 0 | J94: =IF(OR($H94="",$I94=""),"",IFERROR($I94/$H94,0)) -> 0 | K94: 0 | L94: 0 | M94: =IF(OR($K94="",$L94=""),"",IFERROR($L94/$K94,0)) -> 0 | N94: se estan realizando gestiones para brindar apoyo y establecer el programa de ayuda | O94: Recursos Propios | P94: No iniciada | Q94: Informe | T94: =IF($A94="","",TODAY()) -> 46059
A95: 2025 | B95: Secretaría de Planeación y Obras Públicas | C95: META-161 | D95: =IF($C95="","",INDEX(PLAN_DESARROLLO!$B:$B,MATCH($C95,PLAN_DESARROLLO!$A:$A,0))) -> 2024257770031 | E95: =IF($C95="","",INDEX(PLAN_DESARROLLO!$C:$C,MATCH($C95,PLAN_DESARROLLO!$A:$A,0))) -> POR EL SUPATÁ SOÑADO AVANZAMOS JUNTOS EN LA LÍNEA ESTRATÉGICA INSTITUCIONAL | F95: =IF($C95="","",INDEX(PLAN_DESARROLLO!$D:$D,MATCH($C95,PLAN_DESARROLLO!$A:$A,0))) -> FORTALECIMIENTO INSTITUCIONAL | G95: =IF($C95="","",INDEX(PLAN_DESARROLLO!$E:$E,MATCH($C95,PLAN_DESARROLLO!$A:$A,0))) -> Implementar un programa anual para la ayuda humanitaria y la atención de la población afectada por desastres y emergencias sanitarias | H95: 1 | I95: 0 | J95: =IF(OR($H95="",$I95=""),"",IFERROR($I95/$H95,0)) -> 0 | K95: 0 | L95: 0 | M95: =IF(OR($K95="",$L95=""),"",IFERROR($L95/$K95,0)) -> 0 | N95: se estan realizando gestiones para brindar apoyo y establecer el programa de ayuda | O95: Recursos Propios | P95: No iniciada | Q95: Informe | T95: =IF($A95="","",TODAY()) -> 46059
A96: 2024 | B96: Secretaría de Planeación y Obras Públicas | C96: META-162 | D96: =IF($C96="","",INDEX(PLAN_DESARROLLO!$B:$B,MATCH($C96,PLAN_DESARROLLO!$A:$A,0))) -> 2024257770031 | E96: =IF($C96="","",INDEX(PLAN_DESARROLLO!$C:$C,MATCH($C96,PLAN_DESARROLLO!$A:$A,0))) -> POR EL SUPATÁ SOÑADO AVANZAMOS JUNTOS EN LA LÍNEA ESTRATÉGICA INSTITUCIONAL | F96: =IF($C96="","",INDEX(PLAN_DESARROLLO!$D:$D,MATCH($C96,PLAN_DESARROLLO!$A:$A,0))) -> FORTALECIMIENTO INSTITUCIONAL | G96: =IF($C96="","",INDEX(PLAN_DESARROLLO!$E:$E,MATCH($C96,PLAN_DESARROLLO!$A:$A,0))) -> Realizar ( 4) capacitaciones del comité Local de Atención y Prevención de Desastres en atención y prevención del riesgo | H96: 4 | I96: 2 | J96: =IF(OR($H96="",$I96=""),"",IFERROR($I96/$H96,0)) -> 0.5 | K96: 0 | L96: 0 | M96: =IF(OR($K96="",$L96=""),"",IFERROR($L96/$K96,0)) -> 0 | N96: =N90 -> en conjunto con el convenio del cuerpo de bomberos de san francisoc se brindan capacitaciones | O96: Recursos Propios | P96: En ejecución | Q96: Informe | T96: =IF($A96="","",TODAY()) -> 46059
A97: 2025 | B97: Secretaría de Planeación y Obras Públicas | C97: META-162 | D97: =IF($C97="","",INDEX(PLAN_DESARROLLO!$B:$B,MATCH($C97,PLAN_DESARROLLO!$A:$A,0))) -> 2024257770031 | E97: =IF($C97="","",INDEX(PLAN_DESARROLLO!$C:$C,MATCH($C97,PLAN_DESARROLLO!$A:$A,0))) -> POR EL SUPATÁ SOÑADO AVANZAMOS JUNTOS EN LA LÍNEA ESTRATÉGICA INSTITUCIONAL | F97: =IF($C97="","",INDEX(PLAN_DESARROLLO!$D:$D,MATCH($C97,PLAN_DESARROLLO!$A:$A,0))) -> FORTALECIMIENTO INSTITUCIONAL | G97: =IF($C97="","",INDEX(PLAN_DESARROLLO!$E:$E,MATCH($C97,PLAN_DESARROLLO!$A:$A,0))) -> Realizar ( 4) capacitaciones del comité Local de Atención y Prevención de Desastres en atención y prevención del riesgo | H97: 4 | I97: 2 | J97: =IF(OR($H97="",$I97=""),"",IFERROR($I97/$H97,0)) -> 0.5 | K97: 0 | L97: 0 | M97: =IF(OR($K97="",$L97=""),"",IFERROR($L97/$K97,0)) -> 0 | N97: =N91 -> en conjunto con el convenio del cuerpo de bomberos de san francisoc se brindan capacitaciones | O97: Recursos Propios | P97: En ejecución | Q97: Informe | T97: =IF($A97="","",TODAY()) -> 46059
A98: 2024 | B98: Secretaría de Planeación y Obras Públicas | C98: META-165 | D98: =IF($C98="","",INDEX(PLAN_DESARROLLO!$B:$B,MATCH($C98,PLAN_DESARROLLO!$A:$A,0))) -> 2024257770032 | E98: =IF($C98="","",INDEX(PLAN_DESARROLLO!$C:$C,MATCH($C98,PLAN_DESARROLLO!$A:$A,0))) -> POR EL SUPATÁ SOÑADO AVANZAMOS JUNTOS EN LA LÍNEA ESTRATÉGICA INSTITUCIONAL | F98: =IF($C98="","",INDEX(PLAN_DESARROLLO!$D:$D,MATCH($C98,PLAN_DESARROLLO!$A:$A,0))) -> DESARROLLO COMUNITARIO | G98: =IF($C98="","",INDEX(PLAN_DESARROLLO!$E:$E,MATCH($C98,PLAN_DESARROLLO!$A:$A,0))) -> Realizar 4 rendiciones de cuentas sobre la gestión de la administración municipal. | H98: 4 | I98: 2 | J98: =IF(OR($H98="",$I98=""),"",IFERROR($I98/$H98,0)) -> 0.5 | K98: 0 | L98: 0 | M98: =IF(OR($K98="",$L98=""),"",IFERROR($L98/$K98,0)) -> 0 | N98: en espacios oficiales, y reuniones con las veredas y las juntas de accion comunal se informa, y adelanta gestiones realizadas por la administracion municipal | O98: Recursos Propios | P98: En ejecución | Q98: Informe | T98: =IF($A98="","",TODAY()) -> 46059
A99: 2025 | B99: Secretaría de Planeación y Obras Públicas | C99: META-165 | D99: =IF($C99="","",INDEX(PLAN_DESARROLLO!$B:$B,MATCH($C99,PLAN_DESARROLLO!$A:$A,0))) -> 2024257770032 | E99: =IF($C99="","",INDEX(PLAN_DESARROLLO!$C:$C,MATCH($C99,PLAN_DESARROLLO!$A:$A,0))) -> POR EL SUPATÁ SOÑADO AVANZAMOS JUNTOS EN LA LÍNEA ESTRATÉGICA INSTITUCIONAL | F99: =IF($C99="","",INDEX(PLAN_DESARROLLO!$D:$D,MATCH($C99,PLAN_DESARROLLO!$A:$A,0))) -> DESARROLLO COMUNITARIO | G99: =IF($C99="","",INDEX(PLAN_DESARROLLO!$E:$E,MATCH($C99,PLAN_DESARROLLO!$A:$A,0))) -> Realizar 4 rendiciones de cuentas sobre la gestión de la administración municipal. | H99: 4 | I99: 4 | J99: =IF(OR($H99="",$I99=""),"",IFERROR($I99/$H99,0)) -> 1 | K99: 0 | L99: 0 | M99: =IF(OR($K99="",$L99=""),"",IFERROR($L99/$K99,0)) -> 0 | N99: en espacios oficiales, y reuniones con las veredas y las juntas de accion comunal se informa, y adelanta gestiones realizadas por la administracion municipal | O99: Recursos Propios | P99: En ejecución | Q99: Informe | T99: =IF($A99="","",TODAY()) -> 46059
A100: 2024 | B100: Secretaría de Planeación y Obras Públicas | C100: META-179 | D100: =IF($C100="","",INDEX(PLAN_DESARROLLO!$B:$B,MATCH($C100,PLAN_DESARROLLO!$A:$A,0))) -> 2024257770038 | E100: =IF($C100="","",INDEX(PLAN_DESARROLLO!$C:$C,MATCH($C100,PLAN_DESARROLLO!$A:$A,0))) -> POR EL SUPATÁ SOÑADO AVANZAMOS JUNTOS EN LA LÍNEA ESTRATÉGICA AMBIENTAL | F100: =IF($C100="","",INDEX(PLAN_DESARROLLO!$D:$D,MATCH($C100,PLAN_DESARROLLO!$A:$A,0))) -> SERVICIOS DIFERENTES APSB | G100: =IF($C100="","",INDEX(PLAN_DESARROLLO!$E:$E,MATCH($C100,PLAN_DESARROLLO!$A:$A,0))) -> Realizar la ampliación del sistema de alumbrado publico | H100: 1 | I100: 0 | J100: =IF(OR($H100="",$I100=""),"",IFERROR($I100/$H100,0)) -> 0 | K100: 0 | L100: 0 | M100: =IF(OR($K100="",$L100=""),"",IFERROR($L100/$K100,0)) -> 0 | T100: =IF($A100="","",TODAY()) -> 46059
A101: 2025 | B101: Secretaría de Planeación y Obras Públicas | C101: META-179 | D101: =IF($C101="","",INDEX(PLAN_DESARROLLO!$B:$B,MATCH($C101,PLAN_DESARROLLO!$A:$A,0))) -> 2024257770038 | E101: =IF($C101="","",INDEX(PLAN_DESARROLLO!$C:$C,MATCH($C101,PLAN_DESARROLLO!$A:$A,0))) -> POR EL SUPATÁ SOÑADO AVANZAMOS JUNTOS EN LA LÍNEA ESTRATÉGICA AMBIENTAL | F101: =IF($C101="","",INDEX(PLAN_DESARROLLO!$D:$D,MATCH($C101,PLAN_DESARROLLO!$A:$A,0))) -> SERVICIOS DIFERENTES APSB | G101: =IF($C101="","",INDEX(PLAN_DESARROLLO!$E:$E,MATCH($C101,PLAN_DESARROLLO!$A:$A,0))) -> Realizar la ampliación del sistema de alumbrado publico | H101: 1 | I101: 1 | J101: =IF(OR($H101="",$I101=""),"",IFERROR($I101/$H101,0)) -> 1 | K101: 24084074 | L101: 24084074 | M101: =IF(OR($K101="",$L101=""),"",IFERROR($L101/$K101,0)) -> 1 | N101: Ampliacion del sistema de alumbrado publico en el escenario depotivo cancha de futbol Contrato de Compra No. COM-003-2025 | O101: SGP | P101: Cumplida | Q101: Informe | T101: =IF($A101="","",TODAY()) -> 46059
A102: 2024 | B102: Secretaría de Planeación y Obras Públicas | C102: META-180 | D102: =IF($C102="","",INDEX(PLAN_DESARROLLO!$B:$B,MATCH($C102,PLAN_DESARROLLO!$A:$A,0))) -> 2024257770038 | E102: =IF($C102="","",INDEX(PLAN_DESARROLLO!$C:$C,MATCH($C102,PLAN_DESARROLLO!$A:$A,0))) -> POR EL SUPATÁ SOÑADO AVANZAMOS JUNTOS EN LA LÍNEA ESTRATÉGICA AMBIENTAL | F102: =IF($C102="","",INDEX(PLAN_DESARROLLO!$D:$D,MATCH($C102,PLAN_DESARROLLO!$A:$A,0))) -> SERVICIOS DIFERENTES APSB | G102: =IF($C102="","",INDEX(PLAN_DESARROLLO!$E:$E,MATCH($C102,PLAN_DESARROLLO!$A:$A,0))) -> Garantizar el optimo funcionamiento del sistema de alummbrado público | H102: 1 | I102: 1 | J102: =IF(OR($H102="",$I102=""),"",IFERROR($I102/$H102,0)) -> 1 | K102: 32429330 | L102: 32429330 | M102: =IF(OR($K102="",$L102=""),"",IFERROR($L102/$K102,0)) -> 1 | N102: Compra de materiales electricos y prestacion de servicios del tecnico electricists para el mantenimiento del sistema de alumbrado público. | O102: SGP | P102: Cumplida | Q102: Informe | T102: =IF($A102="","",TODAY()) -> 46059
A103: 2025 | B103: Secretaría de Planeación y Obras Públicas | C103: META-180 | D103: =IF($C103="","",INDEX(PLAN_DESARROLLO!$B:$B,MATCH($C103,PLAN_DESARROLLO!$A:$A,0))) -> 2024257770038 | E103: =IF($C103="","",INDEX(PLAN_DESARROLLO!$C:$C,MATCH($C103,PLAN_DESARROLLO!$A:$A,0))) -> POR EL SUPATÁ SOÑADO AVANZAMOS JUNTOS EN LA LÍNEA ESTRATÉGICA AMBIENTAL | F103: =IF($C103="","",INDEX(PLAN_DESARROLLO!$D:$D,MATCH($C103,PLAN_DESARROLLO!$A:$A,0))) -> SERVICIOS DIFERENTES APSB | G103: =IF($C103="","",INDEX(PLAN_DESARROLLO!$E:$E,MATCH($C103,PLAN_DESARROLLO!$A:$A,0))) -> Garantizar el optimo funcionamiento del sistema de alummbrado público | H103: 1 | I103: 1 | J103: =IF(OR($H103="",$I103=""),"",IFERROR($I103/$H103,0)) -> 1 | M103: =IF(OR($K103="",$L103=""),"",IFERROR($L103/$K103,0)) | N103: Compra de materiales electricos y prestacion de servicios del tecnico electricists para el mantenimiento del sistema de alumbrado público. | O103: SGP | P103: Cumplida | Q103: Informe | T103: =IF($A103="","",TODAY()) -> 46059
A104: 2024 | B104: Secretaría de Planeación y Obras Públicas | C104: META-181 | D104: =IF($C104="","",INDEX(PLAN_DESARROLLO!$B:$B,MATCH($C104,PLAN_DESARROLLO!$A:$A,0))) -> 2024257770038 | E104: =IF($C104="","",INDEX(PLAN_DESARROLLO!$C:$C,MATCH($C104,PLAN_DESARROLLO!$A:$A,0))) -> POR EL SUPATÁ SOÑADO AVANZAMOS JUNTOS EN LA LÍNEA ESTRATÉGICA AMBIENTAL | F104: =IF($C104="","",INDEX(PLAN_DESARROLLO!$D:$D,MATCH($C104,PLAN_DESARROLLO!$A:$A,0))) -> SERVICIOS DIFERENTES APSB | G104: =IF($C104="","",INDEX(PLAN_DESARROLLO!$E:$E,MATCH($C104,PLAN_DESARROLLO!$A:$A,0))) -> Realizar anualmente los pagos de servicio de alumbrado público | H104: 1 | I104: 1 | J104: =IF(OR($H104="",$I104=""),"",IFERROR($I104/$H104,0)) -> 1 | K104: 117530733 | L104: 117530733 | M104: =IF(OR($K104="",$L104=""),"",IFERROR($L104/$K104,0)) -> 1 | N104: Pago por servicio de energia consumida en el servicio de alumbrado publico vigencia 2024 | O104: SGP | P104: Cumplida | Q104: Informe | T104: =IF($A104="","",TODAY()) -> 46059
...
